core_vhdl_files/multiplier.vhdl
-- 32-bit Signed Integer Multiplier
-- Only lower 32 bits of result are kept (truncation)
library IEEE;
use IEEE.STD_LOGIC_1164.ALL;
use IEEE.NUMERIC_STD.ALL;

entity multiplier_32 is
    generic (DATA_WIDTH : integer := 32);
    port (
        a : in STD_LOGIC_VECTOR(DATA_WIDTH-1 downto 0);
        b : in STD_LOGIC_VECTOR(DATA_WIDTH-1 downto 0);
        y : out STD_LOGIC_VECTOR(DATA_WIDTH-1 downto 0)
    );
end multiplier_32;

architecture Behavioral of multiplier_32 is
    signal product : signed(2*DATA_WIDTH-1 downto 0);
begin
    -- Full 64-bit signed multiplication
    product <= signed(a) * signed(b);
    -- Keep only lower 32 bits
    y <= std_logic_vector(product(DATA_WIDTH-1 downto 0));
end Behavioral;

core_vhdl_files/adder.vhdl
-- 32-bit Signed Integer Adder
-- Overflow is ignored (C semantics): result wraps around
library IEEE;
use IEEE.STD_LOGIC_1164.ALL;
use IEEE.NUMERIC_STD.ALL;

entity adder_32 is
    generic (DATA_WIDTH : integer := 32);
    port (
        a : in STD_LOGIC_VECTOR(DATA_WIDTH-1 downto 0);
        b : in STD_LOGIC_VECTOR(DATA_WIDTH-1 downto 0);
        y : out STD_LOGIC_VECTOR(DATA_WIDTH-1 downto 0)
    );
end adder_32;

architecture Behavioral of adder_32 is
begin
    -- Signed addition, overflow naturally wraps in 32-bit result
    y <= std_logic_vector(signed(a) + signed(b));
end Behavioral;

core_vhdl_files/dual_port_ram.vhdl
-- dual_port_RAM.vhd

-- created by   :   Meher Krishna Patel
-- date         :   26-Dec-16

-- Functionality:
-- store and retrieve data from single port RAM

-- ports:
-- we         : write enable
-- addr_wr    : address for writing data
-- addr_rd     : address for reading
-- din        : input data to be stored in RAM
-- data       : output data read from RAM
-- addr_width : total number of elements to store (put exact number)
-- addr_bits  : bits requires to store elements specified by addr_width
-- data_width : number of bits in each elements

-- Got some help with AI to load RAM content from a file, since the stackoverflow answer was not functioning as expected

library ieee;
use ieee.std_logic_1164.all;
use ieee.numeric_std.all;
use std.textio.all;

entity dual_port_RAM is
    generic (
        addr_width : integer := 2;
        data_width : integer := 32;
        INIT_FILE : string := "ram_content.txt"
    );
    
    port(
        clk: in std_logic;
        we : in std_logic;
        addr_wr, addr_rd : in std_logic_vector(addr_width-1 downto 0);
        din : in std_logic_vector(data_width-1 downto 0);
        dout : out std_logic_vector(data_width-1 downto 0)
        );
end dual_port_RAM;

architecture arch of dual_port_RAM is
    type ram_type is array (2**addr_width-1 downto 0) of std_logic_vector (data_width-1 downto 0);
    
    impure function init_ram(filename : in string) return ram_type is
        file ram_file : text;
        variable ram_line : line;
        variable temp_int : integer;
        variable temp_ram : ram_type;
        variable status : file_open_status;
    begin
        -- Init with zeros
        for i in 0 to 2**addr_width-1 loop
            temp_ram(i) := (others => '0');
        end loop;
        
        file_open(status, ram_file, filename, read_mode);
        if status = open_ok then
            for i in 0 to 2**addr_width-1 loop
                if not endfile(ram_file) then
                    readline(ram_file, ram_line);
                    read(ram_line, temp_int);
                    temp_ram(i) := std_logic_vector(to_signed(temp_int, data_width));
                end if;
            end loop;
            file_close(ram_file);
        else
            report "RAM Init: Could not open file " & filename severity warning;
        end if;
        return temp_ram;
    end function;

    signal ram_dual_port : ram_type := init_ram(INIT_FILE);
begin
    process(clk)
    begin 
        if (clk'event and clk='1') then
            if (we='1') then -- write data to address 'addr_wr'
        -- convert 'addr_wr' type to integer from std_logic_vector
                ram_dual_port(to_integer(unsigned(addr_wr))) <= din;
            end if;
        end if;
    end process;

    -- get address for reading data from 'addr_rd'
    -- convert 'addr_rd' type to integer from std_logic_vector
    dout <= ram_dual_port(to_integer(unsigned(addr_rd)));
end arch;

generated_vhdl_test0/design.vhdl
-- HLS Generated Design
library IEEE;
use IEEE.STD_LOGIC_1164.ALL;
use IEEE.NUMERIC_STD.ALL;

entity Design is
    Port ( clk, rst : in STD_LOGIC;
           state_out : out STD_LOGIC_VECTOR(2 downto 0);
           done : out STD_LOGIC);
end Design;

architecture Behavioral of Design is

    constant DATA_WIDTH : integer := 32;

    type state_type is (S0, S1, S2, S3, S4, S5, S_END);
    signal state : state_type := S0;

    -- Registers
    signal R0_en : STD_LOGIC;
    signal R0_out : STD_LOGIC_VECTOR(DATA_WIDTH-1 downto 0) := (others => '0');
    signal R1_en : STD_LOGIC;
    signal R1_out : STD_LOGIC_VECTOR(DATA_WIDTH-1 downto 0) := (others => '0');
    signal R2_en : STD_LOGIC;
    signal R2_out : STD_LOGIC_VECTOR(DATA_WIDTH-1 downto 0) := (others => '0');
    signal R3_en : STD_LOGIC;
    signal R3_out : STD_LOGIC_VECTOR(DATA_WIDTH-1 downto 0) := (others => '0');
    signal R4_en : STD_LOGIC;
    signal R4_out : STD_LOGIC_VECTOR(DATA_WIDTH-1 downto 0) := (others => '0');
    signal R5_en : STD_LOGIC;
    signal R5_out : STD_LOGIC_VECTOR(DATA_WIDTH-1 downto 0) := (others => '0');
    signal R6_en : STD_LOGIC;
    signal R6_out : STD_LOGIC_VECTOR(DATA_WIDTH-1 downto 0) := (others => '0');
    signal R7_en : STD_LOGIC;
    signal R7_out : STD_LOGIC_VECTOR(DATA_WIDTH-1 downto 0) := (others => '0');
    signal R8_en : STD_LOGIC;
    signal R8_out : STD_LOGIC_VECTOR(DATA_WIDTH-1 downto 0) := (others => '0');

    -- Memory signals
    signal RAM_we : STD_LOGIC;
    signal RAM_addr_wr : STD_LOGIC_VECTOR(1 downto 0);
    signal RAM_addr_rd : STD_LOGIC_VECTOR(1 downto 0);
    signal RAM_din : STD_LOGIC_VECTOR(DATA_WIDTH-1 downto 0);
    signal RAM_dout : STD_LOGIC_VECTOR(DATA_WIDTH-1 downto 0);

    -- Multiplexer signals
    signal Mux_RAM_addr_sel : STD_LOGIC_VECTOR(1 downto 0);
    signal Mux_RAM_addr_out : STD_LOGIC_VECTOR(DATA_WIDTH-1 downto 0) := (others => '0');
    signal Mux_Mul_0_left_sel : STD_LOGIC_VECTOR(0 downto 0);
    signal Mux_Mul_0_left_out : STD_LOGIC_VECTOR(DATA_WIDTH-1 downto 0) := (others => '0');
    signal Mux_Mul_0_right_sel : STD_LOGIC_VECTOR(0 downto 0);
    signal Mux_Mul_0_right_out : STD_LOGIC_VECTOR(DATA_WIDTH-1 downto 0) := (others => '0');
    signal Mux_Add_0_left_sel : STD_LOGIC_VECTOR(0 downto 0);
    signal Mux_Add_0_left_out : STD_LOGIC_VECTOR(DATA_WIDTH-1 downto 0) := (others => '0');
    signal Mux_Add_0_right_sel : STD_LOGIC_VECTOR(0 downto 0);
    signal Mux_Add_0_right_out : STD_LOGIC_VECTOR(DATA_WIDTH-1 downto 0) := (others => '0');
    signal Mux_RAM_data_sel : STD_LOGIC_VECTOR(0 downto 0);
    signal Mux_RAM_data_out : STD_LOGIC_VECTOR(DATA_WIDTH-1 downto 0) := (others => '0');

    -- Operators resources signals
    signal Add_0_a, Add_0_b : STD_LOGIC_VECTOR(DATA_WIDTH-1 downto 0);
    signal Add_0_out : STD_LOGIC_VECTOR(DATA_WIDTH-1 downto 0);
    signal Mul_0_a, Mul_0_b : STD_LOGIC_VECTOR(DATA_WIDTH-1 downto 0);
    signal Mul_0_out : STD_LOGIC_VECTOR(DATA_WIDTH-1 downto 0);

    function encode_state(s: state_type) return STD_LOGIC_VECTOR is
    begin
        case s is
            when S0 => return std_logic_vector(to_unsigned(0, 3));
            when S1 => return std_logic_vector(to_unsigned(1, 3));
            when S2 => return std_logic_vector(to_unsigned(2, 3));
            when S3 => return std_logic_vector(to_unsigned(3, 3));
            when S4 => return std_logic_vector(to_unsigned(4, 3));
            when S5 => return std_logic_vector(to_unsigned(5, 3));
            when S_END => return std_logic_vector(to_unsigned(6, 3));
        end case;
    end function;

begin

    -- ========== Component Instantiations ==========

    -- Memory instances (dual_port_RAM)
    RAM_RAM: entity work.dual_port_RAM
        generic map (addr_width => 2, data_width => DATA_WIDTH, INIT_FILE => "RAM_content.txt")
        port map (clk => clk, we => RAM_we, addr_wr => RAM_addr_wr, addr_rd => RAM_addr_rd, din => RAM_din, dout => RAM_dout);

    -- Adder instances
    Add_0_ADDER: entity work.adder_32
        port map (a => Add_0_a, b => Add_0_b, y => Add_0_out);

    -- Multiplier instances
    Mul_0_MUL: entity work.multiplier_32
        port map (a => Mul_0_a, b => Mul_0_b, y => Mul_0_out);

    -- ========== FSM Controller ==========
    done <= '1' when state = S_END else '0';
    state_out <= encode_state(state);

    process(clk, rst)
    begin
        if rst = '1' then state <= S0;
        elsif rising_edge(clk) then
            case state is
                when S0 => state <= S1;
                when S1 => state <= S2;
                when S2 => state <= S3;
                when S3 => state <= S4;
                when S4 => state <= S5;
                when S5 => state <= S_END;
                when others => state <= S_END;
            end case;
        end if;
    end process;

    -- Control signals
    process(state)
    begin
        R0_en <= '0';
        R1_en <= '0';
        R2_en <= '0';
        R3_en <= '0';
        R4_en <= '0';
        R5_en <= '0';
        R6_en <= '0';
        R7_en <= '0';
        R8_en <= '0';
        RAM_we <= '0';
        Mux_RAM_addr_sel <= (others => '0');
        Mux_Mul_0_left_sel <= (others => '0');
        Mux_Mul_0_right_sel <= (others => '0');
        Mux_Add_0_left_sel <= (others => '0');
        Mux_Add_0_right_sel <= (others => '0');
        Mux_RAM_data_sel <= (others => '0');
        case state is
            when S0 =>
                R7_en <= '1';
                R0_en <= '1';
                R1_en <= '1';
                R4_en <= '1';
            when S1 =>
                R2_en <= '1';
                Mux_RAM_addr_sel <= std_logic_vector(to_unsigned(0, 2));
            when S2 =>
                R3_en <= '1';
                Mux_RAM_addr_sel <= std_logic_vector(to_unsigned(1, 2));
            when S3 =>
                R5_en <= '1';
                R6_en <= '1';
                Mux_Mul_0_left_sel <= std_logic_vector(to_unsigned(0, 1));
                Mux_Mul_0_right_sel <= std_logic_vector(to_unsigned(0, 1));
                Mux_RAM_addr_sel <= std_logic_vector(to_unsigned(2, 2));
            when S4 =>
                R8_en <= '1';
                Mux_Add_0_left_sel <= std_logic_vector(to_unsigned(0, 1));
                Mux_Add_0_right_sel <= std_logic_vector(to_unsigned(0, 1));
            when S5 =>
                RAM_we <= '1';
                Mux_RAM_addr_sel <= std_logic_vector(to_unsigned(3, 2));
                Mux_RAM_data_sel <= std_logic_vector(to_unsigned(0, 1));
            when others => null;
        end case;
    end process;

    -- ========== Datapath ==========

    -- Registers
    process(clk) begin
        if rising_edge(clk) then
            if R0_en = '1' then R0_out <= std_logic_vector(to_signed(0, DATA_WIDTH)); end if;
            if R1_en = '1' then R1_out <= std_logic_vector(to_signed(1, DATA_WIDTH)); end if;
            if R2_en = '1' then R2_out <= RAM_dout; end if;
            if R3_en = '1' then R3_out <= RAM_dout; end if;
            if R4_en = '1' then R4_out <= std_logic_vector(to_signed(2, DATA_WIDTH)); end if;
            if R5_en = '1' then R5_out <= Mul_0_out; end if;
            if R6_en = '1' then R6_out <= RAM_dout; end if;
            if R7_en = '1' then R7_out <= std_logic_vector(to_signed(3, DATA_WIDTH)); end if;
            if R8_en = '1' then R8_out <= Add_0_out; end if;
        end if;
    end process;

    -- Multiplexers
    with Mux_RAM_addr_sel select
        Mux_RAM_addr_out <=
            R0_out when "00",
            R1_out when "01",
            R4_out when "10",
            R7_out when "11",
            (others => '0') when others;
    with Mux_Mul_0_left_sel select
        Mux_Mul_0_left_out <=
            R2_out when "0",
            (others => '0') when others;
    with Mux_Mul_0_right_sel select
        Mux_Mul_0_right_out <=
            R3_out when "0",
            (others => '0') when others;
    with Mux_Add_0_left_sel select
        Mux_Add_0_left_out <=
            R5_out when "0",
            (others => '0') when others;
    with Mux_Add_0_right_sel select
        Mux_Add_0_right_out <=
            R6_out when "0",
            (others => '0') when others;
    with Mux_RAM_data_sel select
        Mux_RAM_data_out <=
            R8_out when "0",
            (others => '0') when others;
    -- Memory connections
    RAM_addr_rd <= Mux_RAM_addr_out(1 downto 0);
    RAM_addr_wr <= Mux_RAM_addr_out(1 downto 0);
    RAM_din <= Mux_RAM_data_out;

    -- Arithmetic connections
    Mul_0_a <= Mux_Mul_0_left_out;
    Mul_0_b <= Mux_Mul_0_right_out;
    Add_0_a <= Mux_Add_0_left_out;
    Add_0_b <= Mux_Add_0_right_out;

end Behavioral;

generated_vhdl_test0/testbench.vhdl
-- Testbench
library IEEE;
use IEEE.STD_LOGIC_1164.ALL;
use IEEE.NUMERIC_STD.ALL;

entity testbench is end testbench;

architecture Behavioral of testbench is
    signal clk : STD_LOGIC := '0';
    signal rst : STD_LOGIC := '1';
    constant CLK_PERIOD : time := 10 ns;
    signal state_out : STD_LOGIC_VECTOR(2 downto 0);
    signal done : STD_LOGIC;
begin
    clk <= not clk after CLK_PERIOD / 2;

    Design_inst: entity work.Design port map (clk => clk, rst => rst, state_out => state_out, done => done);

    process begin
        rst <= '1'; wait for CLK_PERIOD * 2;
        rst <= '0'; wait for CLK_PERIOD * 9;
        wait;
    end process;
end Behavioral;

generated_vhdl_test1/wave.vcd
$date
  Wed Feb  4 12:32:52 2026
$end
$version
  GHDL v0
$end
$timescale
  1 fs
$end
$scope module standard $end
$upscope $end
$scope module textio $end
$upscope $end
$scope module std_logic_1164 $end
$upscope $end
$scope module numeric_std $end
$upscope $end
$scope module testbench $end
$var reg 1 ! clk $end
$var reg 1 " rst $end
$var reg 3 # state_out[2:0] $end
$var reg 1 $ done $end
$scope module design_inst $end
$var reg 1 % clk $end
$var reg 1 & rst $end
$var reg 3 ' state_out[2:0] $end
$var reg 1 ( done $end
$comment state is not handled $end
$var reg 1 ) r0_en $end
$var reg 32 * r0_out[31:0] $end
$var reg 1 + r1_en $end
$var reg 32 , r1_out[31:0] $end
$var reg 1 - r2_en $end
$var reg 32 . r2_out[31:0] $end
$var reg 1 / r3_en $end
$var reg 32 0 r3_out[31:0] $end
$var reg 1 1 r4_en $end
$var reg 32 2 r4_out[31:0] $end
$var reg 1 3 r5_en $end
$var reg 32 4 r5_out[31:0] $end
$var reg 1 5 r6_en $end
$var reg 32 6 r6_out[31:0] $end
$var reg 1 7 r7_en $end
$var reg 32 8 r7_out[31:0] $end
$var reg 1 9 r8_en $end
$var reg 32 : r8_out[31:0] $end
$var reg 1 ; ram_we $end
$var reg 2 < ram_addr_wr[1:0] $end
$var reg 2 = ram_addr_rd[1:0] $end
$var reg 32 > ram_din[31:0] $end
$var reg 32 ? ram_dout[31:0] $end
$var reg 2 @ mux_ram_addr_sel[1:0] $end
$var reg 32 A mux_ram_addr_out[31:0] $end
$var reg 1 B mux_mul_0_left_sel[0:0] $end
$var reg 32 C mux_mul_0_left_out[31:0] $end
$var reg 1 D mux_mul_0_right_sel[0:0] $end
$var reg 32 E mux_mul_0_right_out[31:0] $end
$var reg 1 F mux_add_0_left_sel[0:0] $end
$var reg 32 G mux_add_0_left_out[31:0] $end
$var reg 1 H mux_add_0_right_sel[0:0] $end
$var reg 32 I mux_add_0_right_out[31:0] $end
$var reg 1 J mux_ram_data_sel[0:0] $end
$var reg 32 K mux_ram_data_out[31:0] $end
$var reg 32 L add_0_a[31:0] $end
$var reg 32 M add_0_b[31:0] $end
$var reg 32 N add_0_out[31:0] $end
$var reg 32 O mul_0_a[31:0] $end
$var reg 32 P mul_0_b[31:0] $end
$var reg 32 Q mul_0_out[31:0] $end
$scope module ram_ram $end
$var reg 1 R clk $end
$var reg 1 S we $end
$var reg 2 T addr_wr[1:0] $end
$var reg 2 U addr_rd[1:0] $end
$var reg 32 V din[31:0] $end
$var reg 32 W dout[31:0] $end
$comment ram_dual_port is not handled $end
$upscope $end
$scope module add_0_adder $end
$var reg 32 X a[31:0] $end
$var reg 32 Y b[31:0] $end
$var reg 32 Z y[31:0] $end
$upscope $end
$scope module mul_0_mul $end
$var reg 32 [ a[31:0] $end
$var reg 32 \ b[31:0] $end
$var reg 32 ] y[31:0] $end
$var reg 64 ^ product[63:0] $end
$upscope $end
$upscope $end
$upscope $end
$enddefinitions $end
#0
0!
1"
b000 #
0$
0%
1&
b000 '
0(
1)
b00000000000000000000000000000000 *
1+
b00000000000000000000000000000000 ,
0-
b00000000000000000000000000000000 .
0/
b00000000000000000000000000000000 0
11
b00000000000000000000000000000000 2
03
b00000000000000000000000000000000 4
05
b00000000000000000000000000000000 6
17
b00000000000000000000000000000000 8
09
b00000000000000000000000000000000 :
0;
b00 <
b00 =
b00000000000000000000000000000000 >
b00000000000000000000000000000000 ?
b00 @
b00000000000000000000000000000000 A
b0 B
b00000000000000000000000000000000 C
b0 D
b00000000000000000000000000000000 E
b0 F
b00000000000000000000000000000000 G
b0 H
b00000000000000000000000000000000 I
b0 J
b00000000000000000000000000000000 K
b00000000000000000000000000000000 L
b00000000000000000000000000000000 M
b00000000000000000000000000000000 N
b00000000000000000000000000000000 O
b00000000000000000000000000000000 P
b00000000000000000000000000000000 Q
0R
0S
b00 T
b00 U
b00000000000000000000000000000000 V
b00000000000000000000000000000000 W
b00000000000000000000000000000000 X
b00000000000000000000000000000000 Y
b00000000000000000000000000000000 Z
b00000000000000000000000000000000 [
b00000000000000000000000000000000 \
b00000000000000000000000000000000 ]
b0000000000000000000000000000000000000000000000000000000000000000 ^
#5000000
1!
1%
b00000000000000000000000000000001 ,
b00000000000000000000000000000010 2
b00000000000000000000000000000011 8
1R
#10000000
0!
0%
0R
#15000000
1!
1%
1R
#20000000
0!
0"
0%
0&
0R
#25000000
1!
b001 #
1%
b001 '
0)
0+
1-
01
07
1R
#30000000
0!
0%
0R
#35000000
1!
b010 #
1%
b010 '
0-
1/
b01 <
b01 =
b01 @
b00000000000000000000000000000001 A
1R
b01 T
b01 U
#40000000
0!
0%
0R
#45000000
1!
b011 #
1%
b011 '
0/
13
15
b10 <
b10 =
b10 @
b00000000000000000000000000000010 A
1R
b10 T
b10 U
#50000000
0!
0%
0R
#55000000
1!
b100 #
1%
b100 '
03
05
19
b00 <
b00 =
b00 @
b00000000000000000000000000000000 A
1R
b00 T
b00 U
#60000000
0!
0%
0R
#65000000
1!
b101 #
1%
b101 '
09
1;
b11 <
b11 =
b11 @
b00000000000000000000000000000011 A
1R
1S
b11 T
b11 U
#70000000
0!
0%
0R
#75000000
1!
b110 #
1$
1%
b110 '
1(
0;
b00 <
b00 =
b00 @
b00000000000000000000000000000000 A
1R
0S
b00 T
b00 U
