generated_vhdl_test2/datapath_gen.vhdl
-- Complete Datapath (Auto-Generated)
library IEEE;
use IEEE.STD_LOGIC_1164.ALL;
use IEEE.NUMERIC_STD.ALL;
use std.textio.all;

entity Datapath is
    generic (
        DATA_WIDTH : integer := 32;
        ADDR_WIDTH : integer := 10
    );
    Port ( clk, rst : in STD_LOGIC;
           R0_en : in STD_LOGIC;
           R1_en : in STD_LOGIC;
           R10_en : in STD_LOGIC;
           R11_en : in STD_LOGIC;
           R12_en : in STD_LOGIC;
           R13_en : in STD_LOGIC;
           R14_en : in STD_LOGIC;
           R15_en : in STD_LOGIC;
           R16_en : in STD_LOGIC;
           R17_en : in STD_LOGIC;
           R18_en : in STD_LOGIC;
           R19_en : in STD_LOGIC;
           R2_en : in STD_LOGIC;
           R20_en : in STD_LOGIC;
           R21_en : in STD_LOGIC;
           R22_en : in STD_LOGIC;
           R23_en : in STD_LOGIC;
           R3_en : in STD_LOGIC;
           R4_en : in STD_LOGIC;
           R5_en : in STD_LOGIC;
           R6_en : in STD_LOGIC;
           R7_en : in STD_LOGIC;
           R8_en : in STD_LOGIC;
           R9_en : in STD_LOGIC;
           A_en : in STD_LOGIC;
           A_wr : in STD_LOGIC;
           B_en : in STD_LOGIC;
           B_wr : in STD_LOGIC;
           C_en : in STD_LOGIC;
           C_wr : in STD_LOGIC;
           Mux_A_addr_sel : in STD_LOGIC_VECTOR(3 downto 0);
           Mux_B_addr_sel : in STD_LOGIC_VECTOR(3 downto 0);
           Mux_C_addr_sel : in STD_LOGIC_VECTOR(3 downto 0);
           Mux_C_data_sel : in STD_LOGIC_VECTOR(3 downto 0);
           Mux_Mul_0_left_sel : in STD_LOGIC_VECTOR(3 downto 0);
           Mux_Mul_0_right_sel : in STD_LOGIC_VECTOR(3 downto 0);
           done : out STD_LOGIC);
end Datapath;

architecture Behavioral of Datapath is

    -- Register outputs
    signal R0_out : INTEGER := 0;
    signal R1_out : INTEGER := 0;
    signal R10_out : INTEGER := 0;
    signal R11_out : INTEGER := 0;
    signal R12_out : INTEGER := 0;
    signal R13_out : INTEGER := 0;
    signal R14_out : INTEGER := 0;
    signal R15_out : INTEGER := 0;
    signal R16_out : INTEGER := 0;
    signal R17_out : INTEGER := 0;
    signal R18_out : INTEGER := 0;
    signal R19_out : INTEGER := 0;
    signal R2_out : INTEGER := 0;
    signal R20_out : INTEGER := 0;
    signal R21_out : INTEGER := 0;
    signal R22_out : INTEGER := 0;
    signal R23_out : INTEGER := 0;
    signal R3_out : INTEGER := 0;
    signal R4_out : INTEGER := 0;
    signal R5_out : INTEGER := 0;
    signal R6_out : INTEGER := 0;
    signal R7_out : INTEGER := 0;
    signal R8_out : INTEGER := 0;
    signal R9_out : INTEGER := 0;

    -- Mux outputs
    signal Mux_A_addr_out : INTEGER := 0;
    signal Mux_B_addr_out : INTEGER := 0;
    signal Mux_Mul_0_left_out : INTEGER := 0;
    signal Mux_Mul_0_right_out : INTEGER := 0;
    signal Mux_C_addr_out : INTEGER := 0;
    signal Mux_C_data_out : INTEGER := 0;

    -- Memory data outputs
    signal A_dout : INTEGER := 0;
    signal B_dout : INTEGER := 0;
    signal C_dout : INTEGER := 0;

    -- Arithmetic unit outputs
    signal Mul_0_out : INTEGER := 0;

    -- Memory array type and initialization
    type ram_array is array (0 to 2**ADDR_WIDTH-1) of INTEGER;

    impure function init_ram(filename : in string) return ram_array is
        file ram_file : text;
        variable ram_line : line;
        variable temp_int : integer;
        variable temp_ram : ram_array;
        variable status : file_open_status;
    begin
        for i in 0 to 2**ADDR_WIDTH-1 loop
            temp_ram(i) := 0;
        end loop;
        file_open(status, ram_file, filename, read_mode);
        if status = open_ok then
            for i in 0 to 2**ADDR_WIDTH-1 loop
                if not endfile(ram_file) then
                    readline(ram_file, ram_line);
                    read(ram_line, temp_int);
                    temp_ram(i) := temp_int;
                end if;
            end loop;
            file_close(ram_file);
        end if;
        return temp_ram;
    end function;

    signal A_mem : ram_array := init_ram("A_content.txt");
    signal B_mem : ram_array := init_ram("B_content.txt");
    signal C_mem : ram_array := init_ram("C_content.txt");

begin

    done <= '1';  -- Always done for now

    -- Register update process
    process(clk)
    begin
        if rising_edge(clk) then
            if R0_en = '1' then R0_out <= 0; end if;
            if R1_en = '1' then R1_out <= 0; end if;
            if R10_en = '1' then R10_out <= 1; end if;
            if R11_en = '1' then R11_out <= Mul_0_out; end if;
            if R12_en = '1' then R12_out <= 2; end if;
            if R13_en = '1' then R13_out <= 2; end if;
            if R14_en = '1' then R14_out <= A_dout; end if;
            if R15_en = '1' then R15_out <= B_dout; end if;
            if R16_en = '1' then R16_out <= 2; end if;
            if R17_en = '1' then R17_out <= Mul_0_out; end if;
            if R18_en = '1' then R18_out <= 3; end if;
            if R19_en = '1' then R19_out <= 3; end if;
            if R2_en = '1' then R2_out <= A_dout; end if;
            if R20_en = '1' then R20_out <= A_dout; end if;
            if R21_en = '1' then R21_out <= B_dout; end if;
            if R22_en = '1' then R22_out <= 3; end if;
            if R23_en = '1' then R23_out <= Mul_0_out; end if;
            if R3_en = '1' then R3_out <= B_dout; end if;
            if R4_en = '1' then R4_out <= 0; end if;
            if R5_en = '1' then R5_out <= Mul_0_out; end if;
            if R6_en = '1' then R6_out <= 1; end if;
            if R7_en = '1' then R7_out <= 1; end if;
            if R8_en = '1' then R8_out <= A_dout; end if;
            if R9_en = '1' then R9_out <= B_dout; end if;
        end if;
    end process;

    -- Multiplexer logic
    Mux_A_addr_out <= R0_out when Mux_A_addr_sel = "0000" else
               R6_out when Mux_A_addr_sel = "0001" else
               R12_out when Mux_A_addr_sel = "0010" else
               R18_out when Mux_A_addr_sel = "0011" else 0;

    Mux_B_addr_out <= R1_out when Mux_B_addr_sel = "0000" else
               R7_out when Mux_B_addr_sel = "0001" else
               R13_out when Mux_B_addr_sel = "0010" else
               R19_out when Mux_B_addr_sel = "0011" else 0;

    Mux_Mul_0_left_out <= R2_out when Mux_Mul_0_left_sel = "0000" else
               R8_out when Mux_Mul_0_left_sel = "0001" else
               R14_out when Mux_Mul_0_left_sel = "0010" else
               R20_out when Mux_Mul_0_left_sel = "0011" else 0;

    Mux_Mul_0_right_out <= R3_out when Mux_Mul_0_right_sel = "0000" else
               R9_out when Mux_Mul_0_right_sel = "0001" else
               R15_out when Mux_Mul_0_right_sel = "0010" else
               R21_out when Mux_Mul_0_right_sel = "0011" else 0;

    Mux_C_addr_out <= R4_out when Mux_C_addr_sel = "0000" else
               R10_out when Mux_C_addr_sel = "0001" else
               R16_out when Mux_C_addr_sel = "0010" else
               R22_out when Mux_C_addr_sel = "0011" else 0;

    Mux_C_data_out <= R5_out when Mux_C_data_sel = "0000" else
               R11_out when Mux_C_data_sel = "0001" else
               R17_out when Mux_C_data_sel = "0010" else
               R23_out when Mux_C_data_sel = "0011" else 0;

    -- Memory read logic (combinational)
    A_dout <= A_mem(Mux_A_addr_out);
    B_dout <= B_mem(Mux_B_addr_out);
    C_dout <= C_mem(Mux_C_addr_out);

    -- Memory write processes
    process(clk)
    begin
        if rising_edge(clk) then
            if C_wr = '1' then
                C_mem(Mux_C_addr_out) <= Mux_C_data_out;
            end if;
        end if;
    end process;

    -- Arithmetic units (combinational)
    Mul_0_out <= Mux_Mul_0_left_out * Mux_Mul_0_right_out;

end Behavioral;

generated_vhdl_test2/controller.vhdl
-- FSM Controller
library IEEE;
use IEEE.STD_LOGIC_1164.ALL;
use IEEE.NUMERIC_STD.ALL;

entity Controller is
    Port ( clk, rst : in STD_LOGIC;
           R0_en : out STD_LOGIC;
           R1_en : out STD_LOGIC;
           R10_en : out STD_LOGIC;
           R11_en : out STD_LOGIC;
           R12_en : out STD_LOGIC;
           R13_en : out STD_LOGIC;
           R14_en : out STD_LOGIC;
           R15_en : out STD_LOGIC;
           R16_en : out STD_LOGIC;
           R17_en : out STD_LOGIC;
           R18_en : out STD_LOGIC;
           R19_en : out STD_LOGIC;
           R2_en : out STD_LOGIC;
           R20_en : out STD_LOGIC;
           R21_en : out STD_LOGIC;
           R22_en : out STD_LOGIC;
           R23_en : out STD_LOGIC;
           R3_en : out STD_LOGIC;
           R4_en : out STD_LOGIC;
           R5_en : out STD_LOGIC;
           R6_en : out STD_LOGIC;
           R7_en : out STD_LOGIC;
           R8_en : out STD_LOGIC;
           R9_en : out STD_LOGIC;
           A_en : out STD_LOGIC;
           A_wr : out STD_LOGIC;
           B_en : out STD_LOGIC;
           B_wr : out STD_LOGIC;
           C_en : out STD_LOGIC;
           C_wr : out STD_LOGIC;
           Mux_A_addr_sel : out STD_LOGIC_VECTOR(3 downto 0);
           Mux_B_addr_sel : out STD_LOGIC_VECTOR(3 downto 0);
           Mux_C_addr_sel : out STD_LOGIC_VECTOR(3 downto 0);
           Mux_C_data_sel : out STD_LOGIC_VECTOR(3 downto 0);
           Mux_Mul_0_left_sel : out STD_LOGIC_VECTOR(3 downto 0);
           Mux_Mul_0_right_sel : out STD_LOGIC_VECTOR(3 downto 0);
           state_out : out STD_LOGIC_VECTOR(3 downto 0));
end Controller;

architecture Behavioral of Controller is
    type state_type is (S0, S1, S2, S3, S4, S5, S6, S_END);
    signal state : state_type := S0;
    function encode_state(s: state_type) return STD_LOGIC_VECTOR is
    begin
        case s is
            when S0 => return std_logic_vector(to_unsigned(0, 4));
            when S1 => return std_logic_vector(to_unsigned(1, 4));
            when S2 => return std_logic_vector(to_unsigned(2, 4));
            when S3 => return std_logic_vector(to_unsigned(3, 4));
            when S4 => return std_logic_vector(to_unsigned(4, 4));
            when S5 => return std_logic_vector(to_unsigned(5, 4));
            when S6 => return std_logic_vector(to_unsigned(6, 4));
            when S_END => return std_logic_vector(to_unsigned(7, 4));
        end case;
    end function;
begin

    process(clk, rst)
    begin
        if rst = '1' then state <= S0;
        elsif rising_edge(clk) then
            case state is
                when S0 => state <= S1;
                when S1 => state <= S2;
                when S2 => state <= S3;
                when S3 => state <= S4;
                when S4 => state <= S5;
                when S5 => state <= S6;
                when S6 => state <= S_END;
                when others => state <= S_END;
            end case;
        end if;
    end process;

    state_out <= encode_state(state);

    process(state)
    begin
        R0_en <= '0';
        R1_en <= '0';
        R10_en <= '0';
        R11_en <= '0';
        R12_en <= '0';
        R13_en <= '0';
        R14_en <= '0';
        R15_en <= '0';
        R16_en <= '0';
        R17_en <= '0';
        R18_en <= '0';
        R19_en <= '0';
        R2_en <= '0';
        R20_en <= '0';
        R21_en <= '0';
        R22_en <= '0';
        R23_en <= '0';
        R3_en <= '0';
        R4_en <= '0';
        R5_en <= '0';
        R6_en <= '0';
        R7_en <= '0';
        R8_en <= '0';
        R9_en <= '0';
        A_en <= '0';
        A_wr <= '0';
        B_en <= '0';
        B_wr <= '0';
        C_en <= '0';
        C_wr <= '0';
        Mux_A_addr_sel <= (others => '0');
        Mux_B_addr_sel <= (others => '0');
        Mux_C_addr_sel <= (others => '0');
        Mux_C_data_sel <= (others => '0');
        Mux_Mul_0_left_sel <= (others => '0');
        Mux_Mul_0_right_sel <= (others => '0');
        case state is
            when S0 =>
                R4_en <= '1';
                R0_en <= '1';
                R1_en <= '1';
                R10_en <= '1';
                R6_en <= '1';
                R7_en <= '1';
                R16_en <= '1';
                R12_en <= '1';
                R13_en <= '1';
                R22_en <= '1';
                R18_en <= '1';
                R19_en <= '1';
            when S1 =>
                R2_en <= '1';
                R3_en <= '1';
                A_en <= '1';
                B_en <= '1';
                Mux_A_addr_sel <= std_logic_vector(to_unsigned(0, 4));
                Mux_B_addr_sel <= std_logic_vector(to_unsigned(0, 4));
            when S2 =>
                R5_en <= '1';
                R8_en <= '1';
                R9_en <= '1';
                A_en <= '1';
                B_en <= '1';
                Mux_Mul_0_left_sel <= std_logic_vector(to_unsigned(0, 4));
                Mux_Mul_0_right_sel <= std_logic_vector(to_unsigned(0, 4));
                Mux_A_addr_sel <= std_logic_vector(to_unsigned(1, 4));
                Mux_B_addr_sel <= std_logic_vector(to_unsigned(1, 4));
            when S3 =>
                R11_en <= '1';
                R14_en <= '1';
                R15_en <= '1';
                C_en <= '1';
                C_wr <= '1';
                A_en <= '1';
                B_en <= '1';
                Mux_C_addr_sel <= std_logic_vector(to_unsigned(0, 4));
                Mux_C_data_sel <= std_logic_vector(to_unsigned(0, 4));
                Mux_Mul_0_left_sel <= std_logic_vector(to_unsigned(1, 4));
                Mux_Mul_0_right_sel <= std_logic_vector(to_unsigned(1, 4));
                Mux_A_addr_sel <= std_logic_vector(to_unsigned(2, 4));
                Mux_B_addr_sel <= std_logic_vector(to_unsigned(2, 4));
            when S4 =>
                R17_en <= '1';
                R20_en <= '1';
                R21_en <= '1';
                C_en <= '1';
                C_wr <= '1';
                A_en <= '1';
                B_en <= '1';
                Mux_C_addr_sel <= std_logic_vector(to_unsigned(1, 4));
                Mux_C_data_sel <= std_logic_vector(to_unsigned(1, 4));
                Mux_Mul_0_left_sel <= std_logic_vector(to_unsigned(2, 4));
                Mux_Mul_0_right_sel <= std_logic_vector(to_unsigned(2, 4));
                Mux_A_addr_sel <= std_logic_vector(to_unsigned(3, 4));
                Mux_B_addr_sel <= std_logic_vector(to_unsigned(3, 4));
            when S5 =>
                R23_en <= '1';
                C_en <= '1';
                C_wr <= '1';
                Mux_C_addr_sel <= std_logic_vector(to_unsigned(2, 4));
                Mux_C_data_sel <= std_logic_vector(to_unsigned(2, 4));
                Mux_Mul_0_left_sel <= std_logic_vector(to_unsigned(3, 4));
                Mux_Mul_0_right_sel <= std_logic_vector(to_unsigned(3, 4));
            when S6 =>
                C_en <= '1';
                C_wr <= '1';
                Mux_C_addr_sel <= std_logic_vector(to_unsigned(3, 4));
                Mux_C_data_sel <= std_logic_vector(to_unsigned(3, 4));
            when others => null;
        end case;
    end process;
end Behavioral;

generated_vhdl_test2/testbench.vhdl
-- Testbench for HLS Generated Design
library IEEE;
use IEEE.STD_LOGIC_1164.ALL;
use IEEE.NUMERIC_STD.ALL;

entity testbench is
end testbench;

architecture Behavioral of testbench is
    -- Clock and reset
    signal clk : STD_LOGIC := '0';
    signal rst : STD_LOGIC := '1';
    constant CLK_PERIOD : time := 10 ns;

    -- Control signals (connect Controller to Datapath)
    signal R0_en : STD_LOGIC;
    signal R1_en : STD_LOGIC;
    signal R10_en : STD_LOGIC;
    signal R11_en : STD_LOGIC;
    signal R12_en : STD_LOGIC;
    signal R13_en : STD_LOGIC;
    signal R14_en : STD_LOGIC;
    signal R15_en : STD_LOGIC;
    signal R16_en : STD_LOGIC;
    signal R17_en : STD_LOGIC;
    signal R18_en : STD_LOGIC;
    signal R19_en : STD_LOGIC;
    signal R2_en : STD_LOGIC;
    signal R20_en : STD_LOGIC;
    signal R21_en : STD_LOGIC;
    signal R22_en : STD_LOGIC;
    signal R23_en : STD_LOGIC;
    signal R3_en : STD_LOGIC;
    signal R4_en : STD_LOGIC;
    signal R5_en : STD_LOGIC;
    signal R6_en : STD_LOGIC;
    signal R7_en : STD_LOGIC;
    signal R8_en : STD_LOGIC;
    signal R9_en : STD_LOGIC;
    signal A_en : STD_LOGIC;
    signal A_wr : STD_LOGIC;
    signal B_en : STD_LOGIC;
    signal B_wr : STD_LOGIC;
    signal C_en : STD_LOGIC;
    signal C_wr : STD_LOGIC;
    signal Mux_A_addr_sel : STD_LOGIC_VECTOR(3 downto 0);
    signal Mux_B_addr_sel : STD_LOGIC_VECTOR(3 downto 0);
    signal Mux_C_addr_sel : STD_LOGIC_VECTOR(3 downto 0);
    signal Mux_C_data_sel : STD_LOGIC_VECTOR(3 downto 0);
    signal Mux_Mul_0_left_sel : STD_LOGIC_VECTOR(3 downto 0);
    signal Mux_Mul_0_right_sel : STD_LOGIC_VECTOR(3 downto 0);
    signal state_out : STD_LOGIC_VECTOR(3 downto 0);

    -- Done signal from Datapath
    signal done : STD_LOGIC;

begin

    -- Clock generation
    clk <= not clk after CLK_PERIOD / 2;

    -- Controller instantiation
    CTRL: entity work.Controller
        port map (
            clk => clk,
            rst => rst,
            R0_en => R0_en,
            R1_en => R1_en,
            R10_en => R10_en,
            R11_en => R11_en,
            R12_en => R12_en,
            R13_en => R13_en,
            R14_en => R14_en,
            R15_en => R15_en,
            R16_en => R16_en,
            R17_en => R17_en,
            R18_en => R18_en,
            R19_en => R19_en,
            R2_en => R2_en,
            R20_en => R20_en,
            R21_en => R21_en,
            R22_en => R22_en,
            R23_en => R23_en,
            R3_en => R3_en,
            R4_en => R4_en,
            R5_en => R5_en,
            R6_en => R6_en,
            R7_en => R7_en,
            R8_en => R8_en,
            R9_en => R9_en,
            A_en => A_en,
            A_wr => A_wr,
            B_en => B_en,
            B_wr => B_wr,
            C_en => C_en,
            C_wr => C_wr,
            Mux_A_addr_sel => Mux_A_addr_sel,
            Mux_B_addr_sel => Mux_B_addr_sel,
            Mux_C_addr_sel => Mux_C_addr_sel,
            Mux_C_data_sel => Mux_C_data_sel,
            Mux_Mul_0_left_sel => Mux_Mul_0_left_sel,
            Mux_Mul_0_right_sel => Mux_Mul_0_right_sel,
            state_out => state_out
        );

    -- Datapath instantiation
    DP: entity work.Datapath
        port map (
            clk => clk,
            rst => rst,
            R0_en => R0_en,
            R1_en => R1_en,
            R10_en => R10_en,
            R11_en => R11_en,
            R12_en => R12_en,
            R13_en => R13_en,
            R14_en => R14_en,
            R15_en => R15_en,
            R16_en => R16_en,
            R17_en => R17_en,
            R18_en => R18_en,
            R19_en => R19_en,
            R2_en => R2_en,
            R20_en => R20_en,
            R21_en => R21_en,
            R22_en => R22_en,
            R23_en => R23_en,
            R3_en => R3_en,
            R4_en => R4_en,
            R5_en => R5_en,
            R6_en => R6_en,
            R7_en => R7_en,
            R8_en => R8_en,
            R9_en => R9_en,
            A_en => A_en,
            A_wr => A_wr,
            B_en => B_en,
            B_wr => B_wr,
            C_en => C_en,
            C_wr => C_wr,
            Mux_A_addr_sel => Mux_A_addr_sel,
            Mux_B_addr_sel => Mux_B_addr_sel,
            Mux_C_addr_sel => Mux_C_addr_sel,
            Mux_C_data_sel => Mux_C_data_sel,
            Mux_Mul_0_left_sel => Mux_Mul_0_left_sel,
            Mux_Mul_0_right_sel => Mux_Mul_0_right_sel,
            done => done
        );

    -- Stimulus process
    process
    begin
        rst <= '1';
        wait for CLK_PERIOD * 2;
        rst <= '0';
        wait for CLK_PERIOD * 10;  -- Run all states
        wait;
    end process;

end Behavioral;

generated_vhdl_test2/wave.vcd
$date
  Tue Feb  3 22:29:32 2026
$end
$version
  GHDL v0
$end
$timescale
  1 fs
$end
$scope module standard $end
$upscope $end
$scope module textio $end
$upscope $end
$scope module std_logic_1164 $end
$upscope $end
$scope module numeric_std $end
$upscope $end
$scope module testbench $end
$var reg 1 ! clk $end
$var reg 1 " rst $end
$var reg 1 # r0_en $end
$var reg 1 $ r1_en $end
$var reg 1 % r10_en $end
$var reg 1 & r11_en $end
$var reg 1 ' r12_en $end
$var reg 1 ( r13_en $end
$var reg 1 ) r14_en $end
$var reg 1 * r15_en $end
$var reg 1 + r16_en $end
$var reg 1 , r17_en $end
$var reg 1 - r18_en $end
$var reg 1 . r19_en $end
$var reg 1 / r2_en $end
$var reg 1 0 r20_en $end
$var reg 1 1 r21_en $end
$var reg 1 2 r22_en $end
$var reg 1 3 r23_en $end
$var reg 1 4 r3_en $end
$var reg 1 5 r4_en $end
$var reg 1 6 r5_en $end
$var reg 1 7 r6_en $end
$var reg 1 8 r7_en $end
$var reg 1 9 r8_en $end
$var reg 1 : r9_en $end
$var reg 1 ; a_en $end
$var reg 1 < a_wr $end
$var reg 1 = b_en $end
$var reg 1 > b_wr $end
$var reg 1 ? c_en $end
$var reg 1 @ c_wr $end
$var reg 4 A mux_a_addr_sel[3:0] $end
$var reg 4 B mux_b_addr_sel[3:0] $end
$var reg 4 C mux_c_addr_sel[3:0] $end
$var reg 4 D mux_c_data_sel[3:0] $end
$var reg 4 E mux_mul_0_left_sel[3:0] $end
$var reg 4 F mux_mul_0_right_sel[3:0] $end
$var reg 4 G state_out[3:0] $end
$var reg 1 H done $end
$scope module ctrl $end
$var reg 1 I clk $end
$var reg 1 J rst $end
$var reg 1 K r0_en $end
$var reg 1 L r1_en $end
$var reg 1 M r10_en $end
$var reg 1 N r11_en $end
$var reg 1 O r12_en $end
$var reg 1 P r13_en $end
$var reg 1 Q r14_en $end
$var reg 1 R r15_en $end
$var reg 1 S r16_en $end
$var reg 1 T r17_en $end
$var reg 1 U r18_en $end
$var reg 1 V r19_en $end
$var reg 1 W r2_en $end
$var reg 1 X r20_en $end
$var reg 1 Y r21_en $end
$var reg 1 Z r22_en $end
$var reg 1 [ r23_en $end
$var reg 1 \ r3_en $end
$var reg 1 ] r4_en $end
$var reg 1 ^ r5_en $end
$var reg 1 _ r6_en $end
$var reg 1 ` r7_en $end
$var reg 1 a r8_en $end
$var reg 1 b r9_en $end
$var reg 1 c a_en $end
$var reg 1 d a_wr $end
$var reg 1 e b_en $end
$var reg 1 f b_wr $end
$var reg 1 g c_en $end
$var reg 1 h c_wr $end
$var reg 4 i mux_a_addr_sel[3:0] $end
$var reg 4 j mux_b_addr_sel[3:0] $end
$var reg 4 k mux_c_addr_sel[3:0] $end
$var reg 4 l mux_c_data_sel[3:0] $end
$var reg 4 m mux_mul_0_left_sel[3:0] $end
$var reg 4 n mux_mul_0_right_sel[3:0] $end
$var reg 4 o state_out[3:0] $end
$comment state is not handled $end
$upscope $end
$scope module dp $end
$var reg 1 p clk $end
$var reg 1 q rst $end
$var reg 1 r r0_en $end
$var reg 1 s r1_en $end
$var reg 1 t r10_en $end
$var reg 1 u r11_en $end
$var reg 1 v r12_en $end
$var reg 1 w r13_en $end
$var reg 1 x r14_en $end
$var reg 1 y r15_en $end
$var reg 1 z r16_en $end
$var reg 1 { r17_en $end
$var reg 1 | r18_en $end
$var reg 1 } r19_en $end
$var reg 1 !" r2_en $end
$var reg 1 "" r20_en $end
$var reg 1 #" r21_en $end
$var reg 1 $" r22_en $end
$var reg 1 %" r23_en $end
$var reg 1 &" r3_en $end
$var reg 1 '" r4_en $end
$var reg 1 (" r5_en $end
$var reg 1 )" r6_en $end
$var reg 1 *" r7_en $end
$var reg 1 +" r8_en $end
$var reg 1 ," r9_en $end
$var reg 1 -" a_en $end
$var reg 1 ." a_wr $end
$var reg 1 /" b_en $end
$var reg 1 0" b_wr $end
$var reg 1 1" c_en $end
$var reg 1 2" c_wr $end
$var reg 4 3" mux_a_addr_sel[3:0] $end
$var reg 4 4" mux_b_addr_sel[3:0] $end
$var reg 4 5" mux_c_addr_sel[3:0] $end
$var reg 4 6" mux_c_data_sel[3:0] $end
$var reg 4 7" mux_mul_0_left_sel[3:0] $end
$var reg 4 8" mux_mul_0_right_sel[3:0] $end
$var reg 1 9" done $end
$var integer 32 :" r0_out $end
$var integer 32 ;" r1_out $end
$var integer 32 <" r10_out $end
$var integer 32 =" r11_out $end
$var integer 32 >" r12_out $end
$var integer 32 ?" r13_out $end
$var integer 32 @" r14_out $end
$var integer 32 A" r15_out $end
$var integer 32 B" r16_out $end
$var integer 32 C" r17_out $end
$var integer 32 D" r18_out $end
$var integer 32 E" r19_out $end
$var integer 32 F" r2_out $end
$var integer 32 G" r20_out $end
$var integer 32 H" r21_out $end
$var integer 32 I" r22_out $end
$var integer 32 J" r23_out $end
$var integer 32 K" r3_out $end
$var integer 32 L" r4_out $end
$var integer 32 M" r5_out $end
$var integer 32 N" r6_out $end
$var integer 32 O" r7_out $end
$var integer 32 P" r8_out $end
$var integer 32 Q" r9_out $end
$var integer 32 R" mux_a_addr_out $end
$var integer 32 S" mux_b_addr_out $end
$var integer 32 T" mux_mul_0_left_out $end
$var integer 32 U" mux_mul_0_right_out $end
$var integer 32 V" mux_c_addr_out $end
$var integer 32 W" mux_c_data_out $end
$var integer 32 X" a_dout $end
$var integer 32 Y" b_dout $end
$var integer 32 Z" c_dout $end
$var integer 32 [" mul_0_out $end
$comment a_mem is not handled $end
$comment b_mem is not handled $end
$comment c_mem is not handled $end
$upscope $end
$upscope $end
$enddefinitions $end
#0
0!
1"
1#
1$
1%
0&
1'
1(
0)
0*
1+
0,
1-
1.
0/
00
01
12
03
04
15
06
17
18
09
0:
0;
0<
0=
0>
0?
0@
b0000 A
b0000 B
b0000 C
b0000 D
b0000 E
b0000 F
b0000 G
1H
0I
1J
1K
1L
1M
0N
1O
1P
0Q
0R
1S
0T
1U
1V
0W
0X
0Y
1Z
0[
0\
1]
0^
1_
1`
0a
0b
0c
0d
0e
0f
0g
0h
b0000 i
b0000 j
b0000 k
b0000 l
b0000 m
b0000 n
b0000 o
0p
1q
1r
1s
1t
0u
1v
1w
0x
0y
1z
0{
1|
1}
0!"
0""
0#"
1$"
0%"
0&"
1'"
0("
1)"
1*"
0+"
0,"
0-"
0."
0/"
00"
01"
02"
b0000 3"
b0000 4"
b0000 5"
b0000 6"
b0000 7"
b0000 8"
19"
b0 :"
b0 ;"
b0 <"
b0 ="
b0 >"
b0 ?"
b0 @"
b0 A"
b0 B"
b0 C"
b0 D"
b0 E"
b0 F"
b0 G"
b0 H"
b0 I"
b0 J"
b0 K"
b0 L"
b0 M"
b0 N"
b0 O"
b0 P"
b0 Q"
b0 R"
b0 S"
b0 T"
b0 U"
b0 V"
b0 W"
b1010 X"
b1010 Y"
b1010 Z"
b0 ["
#5000000
1!
1I
1p
b1 <"
b10 >"
b10 ?"
b10 B"
b11 D"
b11 E"
b11 I"
b1 N"
b1 O"
#10000000
0!
0I
0p
#15000000
1!
1I
1p
#20000000
0!
0"
0I
0J
0p
0q
#25000000
1!
0#
0$
0%
0'
0(
0+
0-
0.
1/
02
14
05
07
08
1;
1=
b0001 G
1I
0K
0L
0M
0O
0P
0S
0U
0V
1W
0Z
1\
0]
0_
0`
1c
1e
b0001 o
1p
0r
0s
0t
0v
0w
0z
0|
0}
1!"
0$"
1&"
0'"
0)"
0*"
1-"
1/"
#30000000
0!
0I
0p
#35000000
1!
0/
04
16
19
1:
b0001 A
b0001 B
b0010 G
1I
0W
0\
1^
1a
1b
1c
1e
b0001 i
b0001 j
b0010 o
1p
0!"
0&"
1("
1+"
1,"
b0001 3"
b0001 4"
b1010 F"
b1010 K"
b1 R"
b1 S"
b1010 T"
b1010 U"
b10100 X"
b10100 Y"
b1100100 ["
#40000000
0!
0I
0p
#45000000
1!
1&
1)
1*
06
09
0:
1?
1@
b0010 A
b0010 B
b0001 E
b0001 F
b0011 G
1I
1N
1Q
1R
0^
0a
0b
1c
1e
1g
1h
b0010 i
b0010 j
b0001 m
b0001 n
b0011 o
1p
1u
1x
1y
0("
0+"
0,"
11"
12"
b0010 3"
b0010 4"
b0001 7"
b0001 8"
b1100100 M"
b10100 P"
b10100 Q"
b10 R"
b10 S"
b10100 T"
b10100 U"
b1100100 W"
b1100100 X"
b1100100 Y"
b110010000 ["
#50000000
0!
0I
0p
#55000000
1!
0&
0)
0*
1,
10
11
b0011 A
b0011 B
b0001 C
b0001 D
b0010 E
b0010 F
b0100 G
1I
0N
0Q
0R
1T
1X
1Y
1c
1e
1g
1h
b0011 i
b0011 j
b0001 k
b0001 l
b0010 m
b0010 n
b0100 o
1p
0u
0x
0y
1{
1""
1#"
b0011 3"
b0011 4"
b0001 5"
b0001 6"
b0010 7"
b0010 8"
b110010000 ="
b1100100 @"
b1100100 A"
b11 R"
b11 S"
b1100100 T"
b1100100 U"
b1 V"
b110010000 W"
b0 X"
b0 Y"
b10100 Z"
b10011100010000 ["
#60000000
0!
0I
0p
#65000000
1!
0,
00
01
13
0;
0=
b0000 A
b0000 B
b0010 C
b0010 D
b0011 E
b0011 F
b0101 G
1I
0T
0X
0Y
1[
0c
0e
1g
1h
b0000 i
b0000 j
b0010 k
b0010 l
b0011 m
b0011 n
b0101 o
1p
0{
0""
0#"
1%"
0-"
0/"
b0000 3"
b0000 4"
b0010 5"
b0010 6"
b0011 7"
b0011 8"
b10011100010000 C"
b0 R"
b0 S"
b0 T"
b0 U"
b10 V"
b10011100010000 W"
b1010 X"
b1010 Y"
b1100100 Z"
b0 ["
#70000000
0!
0I
0p
#75000000
1!
03
b0011 C
b0011 D
b0000 E
b0000 F
b0110 G
1I
0[
1g
1h
b0011 k
b0011 l
b0000 m
b0000 n
b0110 o
1p
0%"
b0011 5"
b0011 6"
b0000 7"
b0000 8"
b1010 T"
b1010 U"
b11 V"
b0 W"
b0 Z"
b1100100 ["
#80000000
0!
0I
0p
#85000000
1!
0?
0@
b0000 C
b0000 D
b0111 G
1I
0g
0h
b0000 k
b0000 l
b0111 o
1p
01"
02"
b0000 5"
b0000 6"
b0 V"
b1100100 W"
b1100100 Z"
