core_vhdl_files/multiplier.vhdl
-- 32-bit Signed Integer Multiplier
-- Only lower 32 bits of result are kept (truncation)
library IEEE;
use IEEE.STD_LOGIC_1164.ALL;
use IEEE.NUMERIC_STD.ALL;

entity multiplier_32 is
    generic (DATA_WIDTH : integer := 32);
    port (
        a : in STD_LOGIC_VECTOR(DATA_WIDTH-1 downto 0);
        b : in STD_LOGIC_VECTOR(DATA_WIDTH-1 downto 0);
        y : out STD_LOGIC_VECTOR(DATA_WIDTH-1 downto 0)
    );
end multiplier_32;

architecture Behavioral of multiplier_32 is
    signal product : signed(2*DATA_WIDTH-1 downto 0);
begin
    -- Full 64-bit signed multiplication
    product <= signed(a) * signed(b);
    -- Keep only lower 32 bits
    y <= std_logic_vector(product(DATA_WIDTH-1 downto 0));
end Behavioral;

core_vhdl_files/dual_port_ram.vhdl
-- dual_port_RAM.vhd

-- created by   :   Meher Krishna Patel
-- date         :   26-Dec-16

-- Functionality:
-- store and retrieve data from single port RAM

-- ports:
-- we         : write enable
-- addr_wr    : address for writing data
-- addr_rd     : address for reading
-- din        : input data to be stored in RAM
-- data       : output data read from RAM
-- addr_width : total number of elements to store (put exact number)
-- addr_bits  : bits requires to store elements specified by addr_width
-- data_width : number of bits in each elements

-- Got some help with AI to load RAM content from a file, since the stackoverflow answer was not functioning as expected

library ieee;
use ieee.std_logic_1164.all;
use ieee.numeric_std.all;
use std.textio.all;

entity dual_port_RAM is
    generic (
        addr_width : integer := 2;
        data_width : integer := 32;
        INIT_FILE : string := "ram_content.txt"
    );
    
    port(
        clk: in std_logic;
        we : in std_logic;
        addr_wr, addr_rd : in std_logic_vector(addr_width-1 downto 0);
        din : in std_logic_vector(data_width-1 downto 0);
        dout : out std_logic_vector(data_width-1 downto 0)
        );
end dual_port_RAM;

architecture arch of dual_port_RAM is
    type ram_type is array (2**addr_width-1 downto 0) of std_logic_vector (data_width-1 downto 0);
    
    impure function init_ram(filename : in string) return ram_type is
        file ram_file : text;
        variable ram_line : line;
        variable temp_int : integer;
        variable temp_ram : ram_type;
        variable status : file_open_status;
    begin
        -- Init with zeros
        for i in 0 to 2**addr_width-1 loop
            temp_ram(i) := (others => '0');
        end loop;
        
        file_open(status, ram_file, filename, read_mode);
        if status = open_ok then
            for i in 0 to 2**addr_width-1 loop
                if not endfile(ram_file) then
                    readline(ram_file, ram_line);
                    read(ram_line, temp_int);
                    temp_ram(i) := std_logic_vector(to_signed(temp_int, data_width));
                end if;
            end loop;
            file_close(ram_file);
        else
            report "RAM Init: Could not open file " & filename severity warning;
        end if;
        return temp_ram;
    end function;

    signal ram_dual_port : ram_type := init_ram(INIT_FILE);
begin
    process(clk)
    begin 
        if (clk'event and clk='1') then
            if (we='1') then -- write data to address 'addr_wr'
        -- convert 'addr_wr' type to integer from std_logic_vector
                ram_dual_port(to_integer(unsigned(addr_wr))) <= din;
            end if;
        end if;
    end process;

    -- get address for reading data from 'addr_rd'
    -- convert 'addr_rd' type to integer from std_logic_vector
    dout <= ram_dual_port(to_integer(unsigned(addr_rd)));
end arch;

generated_vhdl_test2/design.vhdl
-- HLS Generated Design
library IEEE;
use IEEE.STD_LOGIC_1164.ALL;
use IEEE.NUMERIC_STD.ALL;

entity Design is
    Port ( clk, rst : in STD_LOGIC;
           state_out : out STD_LOGIC_VECTOR(3 downto 0);
           done : out STD_LOGIC);
end Design;

architecture Behavioral of Design is

    constant DATA_WIDTH : integer := 32;

    type state_type is (S0, S1, S2, S3, S4, S5, S6, S_END);
    signal state : state_type := S0;

    -- Registers
    signal R0_en : STD_LOGIC;
    signal R0_out : STD_LOGIC_VECTOR(DATA_WIDTH-1 downto 0) := (others => '0');
    signal R1_en : STD_LOGIC;
    signal R1_out : STD_LOGIC_VECTOR(DATA_WIDTH-1 downto 0) := (others => '0');
    signal R2_en : STD_LOGIC;
    signal R2_out : STD_LOGIC_VECTOR(DATA_WIDTH-1 downto 0) := (others => '0');
    signal R3_en : STD_LOGIC;
    signal R3_out : STD_LOGIC_VECTOR(DATA_WIDTH-1 downto 0) := (others => '0');
    signal R4_en : STD_LOGIC;
    signal R4_out : STD_LOGIC_VECTOR(DATA_WIDTH-1 downto 0) := (others => '0');
    signal R5_en : STD_LOGIC;
    signal R5_out : STD_LOGIC_VECTOR(DATA_WIDTH-1 downto 0) := (others => '0');
    signal R6_en : STD_LOGIC;
    signal R6_out : STD_LOGIC_VECTOR(DATA_WIDTH-1 downto 0) := (others => '0');
    signal R7_en : STD_LOGIC;
    signal R7_out : STD_LOGIC_VECTOR(DATA_WIDTH-1 downto 0) := (others => '0');
    signal R8_en : STD_LOGIC;
    signal R8_out : STD_LOGIC_VECTOR(DATA_WIDTH-1 downto 0) := (others => '0');
    signal R9_en : STD_LOGIC;
    signal R9_out : STD_LOGIC_VECTOR(DATA_WIDTH-1 downto 0) := (others => '0');
    signal R10_en : STD_LOGIC;
    signal R10_out : STD_LOGIC_VECTOR(DATA_WIDTH-1 downto 0) := (others => '0');
    signal R11_en : STD_LOGIC;
    signal R11_out : STD_LOGIC_VECTOR(DATA_WIDTH-1 downto 0) := (others => '0');
    signal R12_en : STD_LOGIC;
    signal R12_out : STD_LOGIC_VECTOR(DATA_WIDTH-1 downto 0) := (others => '0');
    signal R13_en : STD_LOGIC;
    signal R13_out : STD_LOGIC_VECTOR(DATA_WIDTH-1 downto 0) := (others => '0');
    signal R14_en : STD_LOGIC;
    signal R14_out : STD_LOGIC_VECTOR(DATA_WIDTH-1 downto 0) := (others => '0');
    signal R15_en : STD_LOGIC;
    signal R15_out : STD_LOGIC_VECTOR(DATA_WIDTH-1 downto 0) := (others => '0');
    signal R16_en : STD_LOGIC;
    signal R16_out : STD_LOGIC_VECTOR(DATA_WIDTH-1 downto 0) := (others => '0');
    signal R17_en : STD_LOGIC;
    signal R17_out : STD_LOGIC_VECTOR(DATA_WIDTH-1 downto 0) := (others => '0');
    signal R18_en : STD_LOGIC;
    signal R18_out : STD_LOGIC_VECTOR(DATA_WIDTH-1 downto 0) := (others => '0');
    signal R19_en : STD_LOGIC;
    signal R19_out : STD_LOGIC_VECTOR(DATA_WIDTH-1 downto 0) := (others => '0');
    signal R20_en : STD_LOGIC;
    signal R20_out : STD_LOGIC_VECTOR(DATA_WIDTH-1 downto 0) := (others => '0');
    signal R21_en : STD_LOGIC;
    signal R21_out : STD_LOGIC_VECTOR(DATA_WIDTH-1 downto 0) := (others => '0');
    signal R22_en : STD_LOGIC;
    signal R22_out : STD_LOGIC_VECTOR(DATA_WIDTH-1 downto 0) := (others => '0');
    signal R23_en : STD_LOGIC;
    signal R23_out : STD_LOGIC_VECTOR(DATA_WIDTH-1 downto 0) := (others => '0');

    -- Memory signals
    signal A_we : STD_LOGIC;
    signal A_addr_wr : STD_LOGIC_VECTOR(1 downto 0);
    signal A_addr_rd : STD_LOGIC_VECTOR(1 downto 0);
    signal A_din : STD_LOGIC_VECTOR(DATA_WIDTH-1 downto 0);
    signal A_dout : STD_LOGIC_VECTOR(DATA_WIDTH-1 downto 0);
    signal B_we : STD_LOGIC;
    signal B_addr_wr : STD_LOGIC_VECTOR(1 downto 0);
    signal B_addr_rd : STD_LOGIC_VECTOR(1 downto 0);
    signal B_din : STD_LOGIC_VECTOR(DATA_WIDTH-1 downto 0);
    signal B_dout : STD_LOGIC_VECTOR(DATA_WIDTH-1 downto 0);
    signal C_we : STD_LOGIC;
    signal C_addr_wr : STD_LOGIC_VECTOR(1 downto 0);
    signal C_addr_rd : STD_LOGIC_VECTOR(1 downto 0);
    signal C_din : STD_LOGIC_VECTOR(DATA_WIDTH-1 downto 0);
    signal C_dout : STD_LOGIC_VECTOR(DATA_WIDTH-1 downto 0);

    -- Multiplexer signals
    signal Mux_A_addr_sel : STD_LOGIC_VECTOR(1 downto 0);
    signal Mux_A_addr_out : STD_LOGIC_VECTOR(DATA_WIDTH-1 downto 0) := (others => '0');
    signal Mux_B_addr_sel : STD_LOGIC_VECTOR(1 downto 0);
    signal Mux_B_addr_out : STD_LOGIC_VECTOR(DATA_WIDTH-1 downto 0) := (others => '0');
    signal Mux_Mul_0_left_sel : STD_LOGIC_VECTOR(1 downto 0);
    signal Mux_Mul_0_left_out : STD_LOGIC_VECTOR(DATA_WIDTH-1 downto 0) := (others => '0');
    signal Mux_Mul_0_right_sel : STD_LOGIC_VECTOR(1 downto 0);
    signal Mux_Mul_0_right_out : STD_LOGIC_VECTOR(DATA_WIDTH-1 downto 0) := (others => '0');
    signal Mux_C_addr_sel : STD_LOGIC_VECTOR(1 downto 0);
    signal Mux_C_addr_out : STD_LOGIC_VECTOR(DATA_WIDTH-1 downto 0) := (others => '0');
    signal Mux_C_data_sel : STD_LOGIC_VECTOR(1 downto 0);
    signal Mux_C_data_out : STD_LOGIC_VECTOR(DATA_WIDTH-1 downto 0) := (others => '0');

    -- Operators resources signals
    signal Mul_0_a, Mul_0_b : STD_LOGIC_VECTOR(DATA_WIDTH-1 downto 0);
    signal Mul_0_out : STD_LOGIC_VECTOR(DATA_WIDTH-1 downto 0);

    function encode_state(s: state_type) return STD_LOGIC_VECTOR is
    begin
        case s is
            when S0 => return std_logic_vector(to_unsigned(0, 4));
            when S1 => return std_logic_vector(to_unsigned(1, 4));
            when S2 => return std_logic_vector(to_unsigned(2, 4));
            when S3 => return std_logic_vector(to_unsigned(3, 4));
            when S4 => return std_logic_vector(to_unsigned(4, 4));
            when S5 => return std_logic_vector(to_unsigned(5, 4));
            when S6 => return std_logic_vector(to_unsigned(6, 4));
            when S_END => return std_logic_vector(to_unsigned(7, 4));
        end case;
    end function;

begin

    -- ========== Component Instantiations ==========

    -- Memory instances (dual_port_RAM)
    A_RAM: entity work.dual_port_RAM
        generic map (addr_width => 2, data_width => DATA_WIDTH, INIT_FILE => "A_content.txt")
        port map (clk => clk, we => A_we, addr_wr => A_addr_wr, addr_rd => A_addr_rd, din => A_din, dout => A_dout);
    B_RAM: entity work.dual_port_RAM
        generic map (addr_width => 2, data_width => DATA_WIDTH, INIT_FILE => "B_content.txt")
        port map (clk => clk, we => B_we, addr_wr => B_addr_wr, addr_rd => B_addr_rd, din => B_din, dout => B_dout);
    C_RAM: entity work.dual_port_RAM
        generic map (addr_width => 2, data_width => DATA_WIDTH, INIT_FILE => "C_content.txt")
        port map (clk => clk, we => C_we, addr_wr => C_addr_wr, addr_rd => C_addr_rd, din => C_din, dout => C_dout);

    -- Adder instances

    -- Multiplier instances
    Mul_0_MUL: entity work.multiplier_32
        port map (a => Mul_0_a, b => Mul_0_b, y => Mul_0_out);

    -- ========== FSM Controller ==========
    done <= '1' when state = S_END else '0';
    state_out <= encode_state(state);

    process(clk, rst)
    begin
        if rst = '1' then state <= S0;
        elsif rising_edge(clk) then
            case state is
                when S0 => state <= S1;
                when S1 => state <= S2;
                when S2 => state <= S3;
                when S3 => state <= S4;
                when S4 => state <= S5;
                when S5 => state <= S6;
                when S6 => state <= S_END;
                when others => state <= S_END;
            end case;
        end if;
    end process;

    -- Control signals
    process(state)
    begin
        R0_en <= '0';
        R1_en <= '0';
        R2_en <= '0';
        R3_en <= '0';
        R4_en <= '0';
        R5_en <= '0';
        R6_en <= '0';
        R7_en <= '0';
        R8_en <= '0';
        R9_en <= '0';
        R10_en <= '0';
        R11_en <= '0';
        R12_en <= '0';
        R13_en <= '0';
        R14_en <= '0';
        R15_en <= '0';
        R16_en <= '0';
        R17_en <= '0';
        R18_en <= '0';
        R19_en <= '0';
        R20_en <= '0';
        R21_en <= '0';
        R22_en <= '0';
        R23_en <= '0';
        A_we <= '0';
        B_we <= '0';
        C_we <= '0';
        Mux_A_addr_sel <= (others => '0');
        Mux_B_addr_sel <= (others => '0');
        Mux_Mul_0_left_sel <= (others => '0');
        Mux_Mul_0_right_sel <= (others => '0');
        Mux_C_addr_sel <= (others => '0');
        Mux_C_data_sel <= (others => '0');
        case state is
            when S0 =>
                R4_en <= '1';
                R0_en <= '1';
                R1_en <= '1';
                R10_en <= '1';
                R6_en <= '1';
                R7_en <= '1';
                R16_en <= '1';
                R12_en <= '1';
                R13_en <= '1';
                R22_en <= '1';
                R18_en <= '1';
                R19_en <= '1';
            when S1 =>
                R2_en <= '1';
                R3_en <= '1';
                Mux_A_addr_sel <= std_logic_vector(to_unsigned(0, 2));
                Mux_B_addr_sel <= std_logic_vector(to_unsigned(0, 2));
            when S2 =>
                R5_en <= '1';
                R8_en <= '1';
                R9_en <= '1';
                Mux_Mul_0_left_sel <= std_logic_vector(to_unsigned(0, 2));
                Mux_Mul_0_right_sel <= std_logic_vector(to_unsigned(0, 2));
                Mux_A_addr_sel <= std_logic_vector(to_unsigned(1, 2));
                Mux_B_addr_sel <= std_logic_vector(to_unsigned(1, 2));
            when S3 =>
                R11_en <= '1';
                R14_en <= '1';
                R15_en <= '1';
                C_we <= '1';
                Mux_C_addr_sel <= std_logic_vector(to_unsigned(0, 2));
                Mux_C_data_sel <= std_logic_vector(to_unsigned(0, 2));
                Mux_Mul_0_left_sel <= std_logic_vector(to_unsigned(1, 2));
                Mux_Mul_0_right_sel <= std_logic_vector(to_unsigned(1, 2));
                Mux_A_addr_sel <= std_logic_vector(to_unsigned(2, 2));
                Mux_B_addr_sel <= std_logic_vector(to_unsigned(2, 2));
            when S4 =>
                R17_en <= '1';
                R20_en <= '1';
                R21_en <= '1';
                C_we <= '1';
                Mux_C_addr_sel <= std_logic_vector(to_unsigned(1, 2));
                Mux_C_data_sel <= std_logic_vector(to_unsigned(1, 2));
                Mux_Mul_0_left_sel <= std_logic_vector(to_unsigned(2, 2));
                Mux_Mul_0_right_sel <= std_logic_vector(to_unsigned(2, 2));
                Mux_A_addr_sel <= std_logic_vector(to_unsigned(3, 2));
                Mux_B_addr_sel <= std_logic_vector(to_unsigned(3, 2));
            when S5 =>
                R23_en <= '1';
                C_we <= '1';
                Mux_C_addr_sel <= std_logic_vector(to_unsigned(2, 2));
                Mux_C_data_sel <= std_logic_vector(to_unsigned(2, 2));
                Mux_Mul_0_left_sel <= std_logic_vector(to_unsigned(3, 2));
                Mux_Mul_0_right_sel <= std_logic_vector(to_unsigned(3, 2));
            when S6 =>
                C_we <= '1';
                Mux_C_addr_sel <= std_logic_vector(to_unsigned(3, 2));
                Mux_C_data_sel <= std_logic_vector(to_unsigned(3, 2));
            when others => null;
        end case;
    end process;

    -- ========== Datapath ==========

    -- Registers
    process(clk) begin
        if rising_edge(clk) then
            if R0_en = '1' then R0_out <= std_logic_vector(to_signed(0, DATA_WIDTH)); end if;
            if R1_en = '1' then R1_out <= std_logic_vector(to_signed(0, DATA_WIDTH)); end if;
            if R2_en = '1' then R2_out <= A_dout; end if;
            if R3_en = '1' then R3_out <= B_dout; end if;
            if R4_en = '1' then R4_out <= std_logic_vector(to_signed(0, DATA_WIDTH)); end if;
            if R5_en = '1' then R5_out <= Mul_0_out; end if;
            if R6_en = '1' then R6_out <= std_logic_vector(to_signed(1, DATA_WIDTH)); end if;
            if R7_en = '1' then R7_out <= std_logic_vector(to_signed(1, DATA_WIDTH)); end if;
            if R8_en = '1' then R8_out <= A_dout; end if;
            if R9_en = '1' then R9_out <= B_dout; end if;
            if R10_en = '1' then R10_out <= std_logic_vector(to_signed(1, DATA_WIDTH)); end if;
            if R11_en = '1' then R11_out <= Mul_0_out; end if;
            if R12_en = '1' then R12_out <= std_logic_vector(to_signed(2, DATA_WIDTH)); end if;
            if R13_en = '1' then R13_out <= std_logic_vector(to_signed(2, DATA_WIDTH)); end if;
            if R14_en = '1' then R14_out <= A_dout; end if;
            if R15_en = '1' then R15_out <= B_dout; end if;
            if R16_en = '1' then R16_out <= std_logic_vector(to_signed(2, DATA_WIDTH)); end if;
            if R17_en = '1' then R17_out <= Mul_0_out; end if;
            if R18_en = '1' then R18_out <= std_logic_vector(to_signed(3, DATA_WIDTH)); end if;
            if R19_en = '1' then R19_out <= std_logic_vector(to_signed(3, DATA_WIDTH)); end if;
            if R20_en = '1' then R20_out <= A_dout; end if;
            if R21_en = '1' then R21_out <= B_dout; end if;
            if R22_en = '1' then R22_out <= std_logic_vector(to_signed(3, DATA_WIDTH)); end if;
            if R23_en = '1' then R23_out <= Mul_0_out; end if;
        end if;
    end process;

    -- Multiplexers
    with Mux_A_addr_sel select
        Mux_A_addr_out <=
            R0_out when "00",
            R6_out when "01",
            R12_out when "10",
            R18_out when "11",
            (others => '0') when others;
    with Mux_B_addr_sel select
        Mux_B_addr_out <=
            R1_out when "00",
            R7_out when "01",
            R13_out when "10",
            R19_out when "11",
            (others => '0') when others;
    with Mux_Mul_0_left_sel select
        Mux_Mul_0_left_out <=
            R2_out when "00",
            R8_out when "01",
            R14_out when "10",
            R20_out when "11",
            (others => '0') when others;
    with Mux_Mul_0_right_sel select
        Mux_Mul_0_right_out <=
            R3_out when "00",
            R9_out when "01",
            R15_out when "10",
            R21_out when "11",
            (others => '0') when others;
    with Mux_C_addr_sel select
        Mux_C_addr_out <=
            R4_out when "00",
            R10_out when "01",
            R16_out when "10",
            R22_out when "11",
            (others => '0') when others;
    with Mux_C_data_sel select
        Mux_C_data_out <=
            R5_out when "00",
            R11_out when "01",
            R17_out when "10",
            R23_out when "11",
            (others => '0') when others;
    -- Memory connections
    A_addr_rd <= Mux_A_addr_out(1 downto 0);
    A_addr_wr <= Mux_A_addr_out(1 downto 0);
    B_addr_rd <= Mux_B_addr_out(1 downto 0);
    B_addr_wr <= Mux_B_addr_out(1 downto 0);
    C_addr_rd <= Mux_C_addr_out(1 downto 0);
    C_addr_wr <= Mux_C_addr_out(1 downto 0);
    C_din <= Mux_C_data_out;

    -- Arithmetic connections
    Mul_0_a <= Mux_Mul_0_left_out;
    Mul_0_b <= Mux_Mul_0_right_out;

end Behavioral;

generated_vhdl_test2/testbench.vhdl
-- Testbench
library IEEE;
use IEEE.STD_LOGIC_1164.ALL;
use IEEE.NUMERIC_STD.ALL;

entity testbench is end testbench;

architecture Behavioral of testbench is
    signal clk : STD_LOGIC := '0';
    signal rst : STD_LOGIC := '1';
    constant CLK_PERIOD : time := 10 ns;
    signal state_out : STD_LOGIC_VECTOR(3 downto 0);
    signal done : STD_LOGIC;
begin
    clk <= not clk after CLK_PERIOD / 2;

    Design_inst: entity work.Design port map (clk => clk, rst => rst, state_out => state_out, done => done);

    process begin
        rst <= '1'; wait for CLK_PERIOD * 2;
        rst <= '0'; wait for CLK_PERIOD * 10;
        wait;
    end process;
end Behavioral;

generated_vhdl_test2/wave.vcd
$date
  Wed Feb  4 12:32:53 2026
$end
$version
  GHDL v0
$end
$timescale
  1 fs
$end
$scope module standard $end
$upscope $end
$scope module textio $end
$upscope $end
$scope module std_logic_1164 $end
$upscope $end
$scope module numeric_std $end
$upscope $end
$scope module testbench $end
$var reg 1 ! clk $end
$var reg 1 " rst $end
$var reg 4 # state_out[3:0] $end
$var reg 1 $ done $end
$scope module design_inst $end
$var reg 1 % clk $end
$var reg 1 & rst $end
$var reg 4 ' state_out[3:0] $end
$var reg 1 ( done $end
$comment state is not handled $end
$var reg 1 ) r0_en $end
$var reg 32 * r0_out[31:0] $end
$var reg 1 + r1_en $end
$var reg 32 , r1_out[31:0] $end
$var reg 1 - r2_en $end
$var reg 32 . r2_out[31:0] $end
$var reg 1 / r3_en $end
$var reg 32 0 r3_out[31:0] $end
$var reg 1 1 r4_en $end
$var reg 32 2 r4_out[31:0] $end
$var reg 1 3 r5_en $end
$var reg 32 4 r5_out[31:0] $end
$var reg 1 5 r6_en $end
$var reg 32 6 r6_out[31:0] $end
$var reg 1 7 r7_en $end
$var reg 32 8 r7_out[31:0] $end
$var reg 1 9 r8_en $end
$var reg 32 : r8_out[31:0] $end
$var reg 1 ; r9_en $end
$var reg 32 < r9_out[31:0] $end
$var reg 1 = r10_en $end
$var reg 32 > r10_out[31:0] $end
$var reg 1 ? r11_en $end
$var reg 32 @ r11_out[31:0] $end
$var reg 1 A r12_en $end
$var reg 32 B r12_out[31:0] $end
$var reg 1 C r13_en $end
$var reg 32 D r13_out[31:0] $end
$var reg 1 E r14_en $end
$var reg 32 F r14_out[31:0] $end
$var reg 1 G r15_en $end
$var reg 32 H r15_out[31:0] $end
$var reg 1 I r16_en $end
$var reg 32 J r16_out[31:0] $end
$var reg 1 K r17_en $end
$var reg 32 L r17_out[31:0] $end
$var reg 1 M r18_en $end
$var reg 32 N r18_out[31:0] $end
$var reg 1 O r19_en $end
$var reg 32 P r19_out[31:0] $end
$var reg 1 Q r20_en $end
$var reg 32 R r20_out[31:0] $end
$var reg 1 S r21_en $end
$var reg 32 T r21_out[31:0] $end
$var reg 1 U r22_en $end
$var reg 32 V r22_out[31:0] $end
$var reg 1 W r23_en $end
$var reg 32 X r23_out[31:0] $end
$var reg 1 Y a_we $end
$var reg 2 Z a_addr_wr[1:0] $end
$var reg 2 [ a_addr_rd[1:0] $end
$var reg 32 \ a_din[31:0] $end
$var reg 32 ] a_dout[31:0] $end
$var reg 1 ^ b_we $end
$var reg 2 _ b_addr_wr[1:0] $end
$var reg 2 ` b_addr_rd[1:0] $end
$var reg 32 a b_din[31:0] $end
$var reg 32 b b_dout[31:0] $end
$var reg 1 c c_we $end
$var reg 2 d c_addr_wr[1:0] $end
$var reg 2 e c_addr_rd[1:0] $end
$var reg 32 f c_din[31:0] $end
$var reg 32 g c_dout[31:0] $end
$var reg 2 h mux_a_addr_sel[1:0] $end
$var reg 32 i mux_a_addr_out[31:0] $end
$var reg 2 j mux_b_addr_sel[1:0] $end
$var reg 32 k mux_b_addr_out[31:0] $end
$var reg 2 l mux_mul_0_left_sel[1:0] $end
$var reg 32 m mux_mul_0_left_out[31:0] $end
$var reg 2 n mux_mul_0_right_sel[1:0] $end
$var reg 32 o mux_mul_0_right_out[31:0] $end
$var reg 2 p mux_c_addr_sel[1:0] $end
$var reg 32 q mux_c_addr_out[31:0] $end
$var reg 2 r mux_c_data_sel[1:0] $end
$var reg 32 s mux_c_data_out[31:0] $end
$var reg 32 t mul_0_a[31:0] $end
$var reg 32 u mul_0_b[31:0] $end
$var reg 32 v mul_0_out[31:0] $end
$scope module a_ram $end
$var reg 1 w clk $end
$var reg 1 x we $end
$var reg 2 y addr_wr[1:0] $end
$var reg 2 z addr_rd[1:0] $end
$var reg 32 { din[31:0] $end
$var reg 32 | dout[31:0] $end
$comment ram_dual_port is not handled $end
$upscope $end
$scope module b_ram $end
$var reg 1 } clk $end
$var reg 1 !" we $end
$var reg 2 "" addr_wr[1:0] $end
$var reg 2 #" addr_rd[1:0] $end
$var reg 32 $" din[31:0] $end
$var reg 32 %" dout[31:0] $end
$comment ram_dual_port is not handled $end
$upscope $end
$scope module c_ram $end
$var reg 1 &" clk $end
$var reg 1 '" we $end
$var reg 2 (" addr_wr[1:0] $end
$var reg 2 )" addr_rd[1:0] $end
$var reg 32 *" din[31:0] $end
$var reg 32 +" dout[31:0] $end
$comment ram_dual_port is not handled $end
$upscope $end
$scope module mul_0_mul $end
$var reg 32 ," a[31:0] $end
$var reg 32 -" b[31:0] $end
$var reg 32 ." y[31:0] $end
$var reg 64 /" product[63:0] $end
$upscope $end
$upscope $end
$upscope $end
$enddefinitions $end
#0
0!
1"
b0000 #
0$
0%
1&
b0000 '
0(
1)
b00000000000000000000000000000000 *
1+
b00000000000000000000000000000000 ,
0-
b00000000000000000000000000000000 .
0/
b00000000000000000000000000000000 0
11
b00000000000000000000000000000000 2
03
b00000000000000000000000000000000 4
15
b00000000000000000000000000000000 6
17
b00000000000000000000000000000000 8
09
b00000000000000000000000000000000 :
0;
b00000000000000000000000000000000 <
1=
b00000000000000000000000000000000 >
0?
b00000000000000000000000000000000 @
1A
b00000000000000000000000000000000 B
1C
b00000000000000000000000000000000 D
0E
b00000000000000000000000000000000 F
0G
b00000000000000000000000000000000 H
1I
b00000000000000000000000000000000 J
0K
b00000000000000000000000000000000 L
1M
b00000000000000000000000000000000 N
1O
b00000000000000000000000000000000 P
0Q
b00000000000000000000000000000000 R
0S
b00000000000000000000000000000000 T
1U
b00000000000000000000000000000000 V
0W
b00000000000000000000000000000000 X
0Y
b00 Z
b00 [
bUUUUUUUUUUUUUUUUUUUUUUUUUUUUUUUU \
b00000000000000000000000000001010 ]
0^
b00 _
b00 `
bUUUUUUUUUUUUUUUUUUUUUUUUUUUUUUUU a
b00000000000000000000000000001010 b
0c
b00 d
b00 e
b00000000000000000000000000000000 f
b00000000000000000000000000000000 g
b00 h
b00000000000000000000000000000000 i
b00 j
b00000000000000000000000000000000 k
b00 l
b00000000000000000000000000000000 m
b00 n
b00000000000000000000000000000000 o
b00 p
b00000000000000000000000000000000 q
b00 r
b00000000000000000000000000000000 s
b00000000000000000000000000000000 t
b00000000000000000000000000000000 u
b00000000000000000000000000000000 v
0w
0x
b00 y
b00 z
bUUUUUUUUUUUUUUUUUUUUUUUUUUUUUUUU {
b00000000000000000000000000001010 |
0}
0!"
b00 ""
b00 #"
bUUUUUUUUUUUUUUUUUUUUUUUUUUUUUUUU $"
b00000000000000000000000000001010 %"
0&"
0'"
b00 ("
b00 )"
b00000000000000000000000000000000 *"
b00000000000000000000000000000000 +"
b00000000000000000000000000000000 ,"
b00000000000000000000000000000000 -"
b00000000000000000000000000000000 ."
b0000000000000000000000000000000000000000000000000000000000000000 /"
#5000000
1!
1%
b00000000000000000000000000000001 6
b00000000000000000000000000000001 8
b00000000000000000000000000000001 >
b00000000000000000000000000000010 B
b00000000000000000000000000000010 D
b00000000000000000000000000000010 J
b00000000000000000000000000000011 N
b00000000000000000000000000000011 P
b00000000000000000000000000000011 V
1w
1}
1&"
#10000000
0!
0%
0w
0}
0&"
#15000000
1!
1%
1w
1}
1&"
#20000000
0!
0"
0%
0&
0w
0}
0&"
#25000000
1!
b0001 #
1%
b0001 '
0)
0+
1-
1/
01
05
07
0=
0A
0C
0I
0M
0O
0U
1w
1}
1&"
#30000000
0!
0%
0w
0}
0&"
#35000000
1!
b0010 #
1%
b0010 '
0-
b00000000000000000000000000001010 .
0/
b00000000000000000000000000001010 0
13
19
1;
b01 Z
b01 [
b00000000000000000000000000010100 ]
b01 _
b01 `
b00000000000000000000000000010100 b
b01 h
b00000000000000000000000000000001 i
b01 j
b00000000000000000000000000000001 k
b00000000000000000000000000001010 m
b00000000000000000000000000001010 o
b00000000000000000000000000001010 t
b00000000000000000000000000001010 u
b00000000000000000000000001100100 v
1w
b01 y
b01 z
b00000000000000000000000000010100 |
1}
b01 ""
b01 #"
b00000000000000000000000000010100 %"
1&"
b00000000000000000000000000001010 ,"
b00000000000000000000000000001010 -"
b00000000000000000000000001100100 ."
b0000000000000000000000000000000000000000000000000000000001100100 /"
#40000000
0!
0%
0w
0}
0&"
#45000000
1!
b0011 #
1%
b0011 '
03
b00000000000000000000000001100100 4
09
b00000000000000000000000000010100 :
0;
b00000000000000000000000000010100 <
1?
1E
1G
b10 Z
b10 [
b00000000000000000000000001100100 ]
b10 _
b10 `
b00000000000000000000000001100100 b
1c
b00000000000000000000000001100100 f
b10 h
b00000000000000000000000000000010 i
b10 j
b00000000000000000000000000000010 k
b01 l
b00000000000000000000000000010100 m
b01 n
b00000000000000000000000000010100 o
b00000000000000000000000001100100 s
b00000000000000000000000000010100 t
b00000000000000000000000000010100 u
b00000000000000000000000110010000 v
1w
b10 y
b10 z
b00000000000000000000000001100100 |
1}
b10 ""
b10 #"
b00000000000000000000000001100100 %"
1&"
1'"
b00000000000000000000000001100100 *"
b00000000000000000000000000010100 ,"
b00000000000000000000000000010100 -"
b00000000000000000000000110010000 ."
b0000000000000000000000000000000000000000000000000000000110010000 /"
#50000000
0!
0%
0w
0}
0&"
#55000000
1!
b0100 #
1%
b0100 '
0?
b00000000000000000000000110010000 @
0E
b00000000000000000000000001100100 F
0G
b00000000000000000000000001100100 H
1K
1Q
1S
b11 Z
b11 [
b00000000000000000000000000000000 ]
b11 _
b11 `
b00000000000000000000000000000000 b
b01 d
b01 e
b00000000000000000000000110010000 f
b00000000000000000000000000000000 g
b11 h
b00000000000000000000000000000011 i
b11 j
b00000000000000000000000000000011 k
b10 l
b00000000000000000000000001100100 m
b10 n
b00000000000000000000000001100100 o
b01 p
b00000000000000000000000000000001 q
b01 r
b00000000000000000000000110010000 s
b00000000000000000000000001100100 t
b00000000000000000000000001100100 u
b00000000000000000010011100010000 v
1w
b11 y
b11 z
b00000000000000000000000000000000 |
1}
b11 ""
b11 #"
b00000000000000000000000000000000 %"
1&"
b01 ("
b01 )"
b00000000000000000000000110010000 *"
b00000000000000000000000000000000 +"
b00000000000000000000000001100100 ,"
b00000000000000000000000001100100 -"
b00000000000000000010011100010000 ."
b0000000000000000000000000000000000000000000000000010011100010000 /"
#60000000
0!
0%
0w
0}
0&"
#65000000
1!
b0101 #
1%
b0101 '
0K
b00000000000000000010011100010000 L
0Q
0S
1W
b00 Z
b00 [
b00000000000000000000000000001010 ]
b00 _
b00 `
b00000000000000000000000000001010 b
b10 d
b10 e
b00000000000000000010011100010000 f
b00000000000000000000000000000000 g
b00 h
b00000000000000000000000000000000 i
b00 j
b00000000000000000000000000000000 k
b11 l
b00000000000000000000000000000000 m
b11 n
b00000000000000000000000000000000 o
b10 p
b00000000000000000000000000000010 q
b10 r
b00000000000000000010011100010000 s
b00000000000000000000000000000000 t
b00000000000000000000000000000000 u
b00000000000000000000000000000000 v
1w
b00 y
b00 z
b00000000000000000000000000001010 |
1}
b00 ""
b00 #"
b00000000000000000000000000001010 %"
1&"
b10 ("
b10 )"
b00000000000000000010011100010000 *"
b00000000000000000000000000000000 +"
b00000000000000000000000000000000 ,"
b00000000000000000000000000000000 -"
b00000000000000000000000000000000 ."
b0000000000000000000000000000000000000000000000000000000000000000 /"
#70000000
0!
0%
0w
0}
0&"
