generated_vhdl_test0/datapath_gen.vhdl
-- Complete Datapath (Auto-Generated)
library IEEE;
use IEEE.STD_LOGIC_1164.ALL;
use IEEE.NUMERIC_STD.ALL;
use std.textio.all;

entity Datapath is
    generic (
        DATA_WIDTH : integer := 32;
        ADDR_WIDTH : integer := 10
    );
    Port ( clk, rst : in STD_LOGIC;
           R0_en : in STD_LOGIC;
           R1_en : in STD_LOGIC;
           R2_en : in STD_LOGIC;
           R3_en : in STD_LOGIC;
           R4_en : in STD_LOGIC;
           R5_en : in STD_LOGIC;
           R6_en : in STD_LOGIC;
           R7_en : in STD_LOGIC;
           R8_en : in STD_LOGIC;
           RAM_en : in STD_LOGIC;
           RAM_wr : in STD_LOGIC;
           Mux_Add_0_left_sel : in STD_LOGIC_VECTOR(3 downto 0);
           Mux_Add_0_right_sel : in STD_LOGIC_VECTOR(3 downto 0);
           Mux_Mul_0_left_sel : in STD_LOGIC_VECTOR(3 downto 0);
           Mux_Mul_0_right_sel : in STD_LOGIC_VECTOR(3 downto 0);
           Mux_RAM_addr_sel : in STD_LOGIC_VECTOR(3 downto 0);
           Mux_RAM_data_sel : in STD_LOGIC_VECTOR(3 downto 0);
           done : out STD_LOGIC);
end Datapath;

architecture Behavioral of Datapath is

    -- Register outputs
    signal R0_out : INTEGER := 0;
    signal R1_out : INTEGER := 0;
    signal R2_out : INTEGER := 0;
    signal R3_out : INTEGER := 0;
    signal R4_out : INTEGER := 0;
    signal R5_out : INTEGER := 0;
    signal R6_out : INTEGER := 0;
    signal R7_out : INTEGER := 0;
    signal R8_out : INTEGER := 0;

    -- Mux outputs
    signal Mux_RAM_addr_out : INTEGER := 0;
    signal Mux_Mul_0_left_out : INTEGER := 0;
    signal Mux_Mul_0_right_out : INTEGER := 0;
    signal Mux_Add_0_left_out : INTEGER := 0;
    signal Mux_Add_0_right_out : INTEGER := 0;
    signal Mux_RAM_data_out : INTEGER := 0;

    -- Memory data outputs
    signal RAM_dout : INTEGER := 0;

    -- Arithmetic unit outputs
    signal Add_0_out : INTEGER := 0;
    signal Mul_0_out : INTEGER := 0;

    -- Memory array type and initialization
    type ram_array is array (0 to 2**ADDR_WIDTH-1) of INTEGER;

    impure function init_ram(filename : in string) return ram_array is
        file ram_file : text;
        variable ram_line : line;
        variable temp_int : integer;
        variable temp_ram : ram_array;
        variable status : file_open_status;
    begin
        for i in 0 to 2**ADDR_WIDTH-1 loop
            temp_ram(i) := 0;
        end loop;
        file_open(status, ram_file, filename, read_mode);
        if status = open_ok then
            for i in 0 to 2**ADDR_WIDTH-1 loop
                if not endfile(ram_file) then
                    readline(ram_file, ram_line);
                    read(ram_line, temp_int);
                    temp_ram(i) := temp_int;
                end if;
            end loop;
            file_close(ram_file);
        end if;
        return temp_ram;
    end function;

    signal RAM_mem : ram_array := init_ram("RAM_content.txt");

begin

    done <= '1';  -- Always done for now

    -- Register update process
    process(clk)
    begin
        if rising_edge(clk) then
            if R0_en = '1' then R0_out <= 0; end if;
            if R1_en = '1' then R1_out <= 1; end if;
            if R2_en = '1' then R2_out <= RAM_dout; end if;
            if R3_en = '1' then R3_out <= RAM_dout; end if;
            if R4_en = '1' then R4_out <= 2; end if;
            if R5_en = '1' then R5_out <= Mul_0_out; end if;
            if R6_en = '1' then R6_out <= RAM_dout; end if;
            if R7_en = '1' then R7_out <= 3; end if;
            if R8_en = '1' then R8_out <= Add_0_out; end if;
        end if;
    end process;

    -- Multiplexer logic
    Mux_RAM_addr_out <= R0_out when Mux_RAM_addr_sel = "0000" else
               R1_out when Mux_RAM_addr_sel = "0001" else
               R4_out when Mux_RAM_addr_sel = "0010" else
               R7_out when Mux_RAM_addr_sel = "0011" else 0;

    Mux_Mul_0_left_out <= R2_out when Mux_Mul_0_left_sel = "0000" else
               0;

    Mux_Mul_0_right_out <= R3_out when Mux_Mul_0_right_sel = "0000" else
               0;

    Mux_Add_0_left_out <= R5_out when Mux_Add_0_left_sel = "0000" else
               0;

    Mux_Add_0_right_out <= R6_out when Mux_Add_0_right_sel = "0000" else
               0;

    Mux_RAM_data_out <= R8_out when Mux_RAM_data_sel = "0000" else
               0;

    -- Memory read logic (combinational)
    RAM_dout <= RAM_mem(Mux_RAM_addr_out);

    -- Memory write processes
    process(clk)
    begin
        if rising_edge(clk) then
            if RAM_wr = '1' then
                RAM_mem(Mux_RAM_addr_out) <= Mux_RAM_data_out;
            end if;
        end if;
    end process;

    -- Arithmetic units (combinational)
    Mul_0_out <= Mux_Mul_0_left_out * Mux_Mul_0_right_out;
    Add_0_out <= Mux_Add_0_left_out + Mux_Add_0_right_out;

end Behavioral;

generated_vhdl_test0/controller.vhdl
-- FSM Controller
library IEEE;
use IEEE.STD_LOGIC_1164.ALL;
use IEEE.NUMERIC_STD.ALL;

entity Controller is
    Port ( clk, rst : in STD_LOGIC;
           R0_en : out STD_LOGIC;
           R1_en : out STD_LOGIC;
           R2_en : out STD_LOGIC;
           R3_en : out STD_LOGIC;
           R4_en : out STD_LOGIC;
           R5_en : out STD_LOGIC;
           R6_en : out STD_LOGIC;
           R7_en : out STD_LOGIC;
           R8_en : out STD_LOGIC;
           RAM_en : out STD_LOGIC;
           RAM_wr : out STD_LOGIC;
           Mux_Add_0_left_sel : out STD_LOGIC_VECTOR(3 downto 0);
           Mux_Add_0_right_sel : out STD_LOGIC_VECTOR(3 downto 0);
           Mux_Mul_0_left_sel : out STD_LOGIC_VECTOR(3 downto 0);
           Mux_Mul_0_right_sel : out STD_LOGIC_VECTOR(3 downto 0);
           Mux_RAM_addr_sel : out STD_LOGIC_VECTOR(3 downto 0);
           Mux_RAM_data_sel : out STD_LOGIC_VECTOR(3 downto 0);
           state_out : out STD_LOGIC_VECTOR(2 downto 0));
end Controller;

architecture Behavioral of Controller is
    type state_type is (S0, S1, S2, S3, S4, S5, S_END);
    signal state : state_type := S0;
    function encode_state(s: state_type) return STD_LOGIC_VECTOR is
    begin
        case s is
            when S0 => return std_logic_vector(to_unsigned(0, 3));
            when S1 => return std_logic_vector(to_unsigned(1, 3));
            when S2 => return std_logic_vector(to_unsigned(2, 3));
            when S3 => return std_logic_vector(to_unsigned(3, 3));
            when S4 => return std_logic_vector(to_unsigned(4, 3));
            when S5 => return std_logic_vector(to_unsigned(5, 3));
            when S_END => return std_logic_vector(to_unsigned(6, 3));
        end case;
    end function;
begin

    process(clk, rst)
    begin
        if rst = '1' then state <= S0;
        elsif rising_edge(clk) then
            case state is
                when S0 => state <= S1;
                when S1 => state <= S2;
                when S2 => state <= S3;
                when S3 => state <= S4;
                when S4 => state <= S5;
                when S5 => state <= S_END;
                when others => state <= S_END;
            end case;
        end if;
    end process;

    state_out <= encode_state(state);

    process(state)
    begin
        R0_en <= '0';
        R1_en <= '0';
        R2_en <= '0';
        R3_en <= '0';
        R4_en <= '0';
        R5_en <= '0';
        R6_en <= '0';
        R7_en <= '0';
        R8_en <= '0';
        RAM_en <= '0';
        RAM_wr <= '0';
        Mux_Add_0_left_sel <= (others => '0');
        Mux_Add_0_right_sel <= (others => '0');
        Mux_Mul_0_left_sel <= (others => '0');
        Mux_Mul_0_right_sel <= (others => '0');
        Mux_RAM_addr_sel <= (others => '0');
        Mux_RAM_data_sel <= (others => '0');
        case state is
            when S0 =>
                R7_en <= '1';
                R0_en <= '1';
                R1_en <= '1';
                R4_en <= '1';
            when S1 =>
                R2_en <= '1';
                RAM_en <= '1';
                Mux_RAM_addr_sel <= std_logic_vector(to_unsigned(0, 4));
            when S2 =>
                R3_en <= '1';
                RAM_en <= '1';
                Mux_RAM_addr_sel <= std_logic_vector(to_unsigned(1, 4));
            when S3 =>
                R5_en <= '1';
                R6_en <= '1';
                RAM_en <= '1';
                Mux_Mul_0_left_sel <= std_logic_vector(to_unsigned(0, 4));
                Mux_Mul_0_right_sel <= std_logic_vector(to_unsigned(0, 4));
                Mux_RAM_addr_sel <= std_logic_vector(to_unsigned(2, 4));
            when S4 =>
                R8_en <= '1';
                Mux_Add_0_left_sel <= std_logic_vector(to_unsigned(0, 4));
                Mux_Add_0_right_sel <= std_logic_vector(to_unsigned(0, 4));
            when S5 =>
                RAM_en <= '1';
                RAM_wr <= '1';
                Mux_RAM_addr_sel <= std_logic_vector(to_unsigned(3, 4));
                Mux_RAM_data_sel <= std_logic_vector(to_unsigned(0, 4));
            when others => null;
        end case;
    end process;
end Behavioral;

generated_vhdl_test0/testbench.vhdl
-- Testbench for HLS Generated Design
library IEEE;
use IEEE.STD_LOGIC_1164.ALL;
use IEEE.NUMERIC_STD.ALL;

entity testbench is
end testbench;

architecture Behavioral of testbench is
    -- Clock and reset
    signal clk : STD_LOGIC := '0';
    signal rst : STD_LOGIC := '1';
    constant CLK_PERIOD : time := 10 ns;

    -- Control signals (connect Controller to Datapath)
    signal R0_en : STD_LOGIC;
    signal R1_en : STD_LOGIC;
    signal R2_en : STD_LOGIC;
    signal R3_en : STD_LOGIC;
    signal R4_en : STD_LOGIC;
    signal R5_en : STD_LOGIC;
    signal R6_en : STD_LOGIC;
    signal R7_en : STD_LOGIC;
    signal R8_en : STD_LOGIC;
    signal RAM_en : STD_LOGIC;
    signal RAM_wr : STD_LOGIC;
    signal Mux_Add_0_left_sel : STD_LOGIC_VECTOR(3 downto 0);
    signal Mux_Add_0_right_sel : STD_LOGIC_VECTOR(3 downto 0);
    signal Mux_Mul_0_left_sel : STD_LOGIC_VECTOR(3 downto 0);
    signal Mux_Mul_0_right_sel : STD_LOGIC_VECTOR(3 downto 0);
    signal Mux_RAM_addr_sel : STD_LOGIC_VECTOR(3 downto 0);
    signal Mux_RAM_data_sel : STD_LOGIC_VECTOR(3 downto 0);
    signal state_out : STD_LOGIC_VECTOR(2 downto 0);

    -- Done signal from Datapath
    signal done : STD_LOGIC;

begin

    -- Clock generation
    clk <= not clk after CLK_PERIOD / 2;

    -- Controller instantiation
    CTRL: entity work.Controller
        port map (
            clk => clk,
            rst => rst,
            R0_en => R0_en,
            R1_en => R1_en,
            R2_en => R2_en,
            R3_en => R3_en,
            R4_en => R4_en,
            R5_en => R5_en,
            R6_en => R6_en,
            R7_en => R7_en,
            R8_en => R8_en,
            RAM_en => RAM_en,
            RAM_wr => RAM_wr,
            Mux_Add_0_left_sel => Mux_Add_0_left_sel,
            Mux_Add_0_right_sel => Mux_Add_0_right_sel,
            Mux_Mul_0_left_sel => Mux_Mul_0_left_sel,
            Mux_Mul_0_right_sel => Mux_Mul_0_right_sel,
            Mux_RAM_addr_sel => Mux_RAM_addr_sel,
            Mux_RAM_data_sel => Mux_RAM_data_sel,
            state_out => state_out
        );

    -- Datapath instantiation
    DP: entity work.Datapath
        port map (
            clk => clk,
            rst => rst,
            R0_en => R0_en,
            R1_en => R1_en,
            R2_en => R2_en,
            R3_en => R3_en,
            R4_en => R4_en,
            R5_en => R5_en,
            R6_en => R6_en,
            R7_en => R7_en,
            R8_en => R8_en,
            RAM_en => RAM_en,
            RAM_wr => RAM_wr,
            Mux_Add_0_left_sel => Mux_Add_0_left_sel,
            Mux_Add_0_right_sel => Mux_Add_0_right_sel,
            Mux_Mul_0_left_sel => Mux_Mul_0_left_sel,
            Mux_Mul_0_right_sel => Mux_Mul_0_right_sel,
            Mux_RAM_addr_sel => Mux_RAM_addr_sel,
            Mux_RAM_data_sel => Mux_RAM_data_sel,
            done => done
        );

    -- Stimulus process
    process
    begin
        rst <= '1';
        wait for CLK_PERIOD * 2;
        rst <= '0';
        wait for CLK_PERIOD * 9;  -- Run all states
        wait;
    end process;

end Behavioral;

generated_vhdl_test0/wave.vcd
$date
  Tue Feb  3 19:51:22 2026
$end
$version
  GHDL v0
$end
$timescale
  1 fs
$end
$scope module standard $end
$upscope $end
$scope module textio $end
$upscope $end
$scope module std_logic_1164 $end
$upscope $end
$scope module numeric_std $end
$upscope $end
$scope module testbench $end
$var reg 1 ! clk $end
$var reg 1 " rst $end
$var reg 1 # r0_en $end
$var reg 1 $ r1_en $end
$var reg 1 % r2_en $end
$var reg 1 & r3_en $end
$var reg 1 ' r4_en $end
$var reg 1 ( r5_en $end
$var reg 1 ) r6_en $end
$var reg 1 * r7_en $end
$var reg 1 + r8_en $end
$var reg 1 , ram_en $end
$var reg 1 - ram_wr $end
$var reg 4 . mux_add_0_left_sel[3:0] $end
$var reg 4 / mux_add_0_right_sel[3:0] $end
$var reg 4 0 mux_mul_0_left_sel[3:0] $end
$var reg 4 1 mux_mul_0_right_sel[3:0] $end
$var reg 4 2 mux_ram_addr_sel[3:0] $end
$var reg 4 3 mux_ram_data_sel[3:0] $end
$var reg 3 4 state_out[2:0] $end
$var reg 1 5 done $end
$scope module ctrl $end
$var reg 1 6 clk $end
$var reg 1 7 rst $end
$var reg 1 8 r0_en $end
$var reg 1 9 r1_en $end
$var reg 1 : r2_en $end
$var reg 1 ; r3_en $end
$var reg 1 < r4_en $end
$var reg 1 = r5_en $end
$var reg 1 > r6_en $end
$var reg 1 ? r7_en $end
$var reg 1 @ r8_en $end
$var reg 1 A ram_en $end
$var reg 1 B ram_wr $end
$var reg 4 C mux_add_0_left_sel[3:0] $end
$var reg 4 D mux_add_0_right_sel[3:0] $end
$var reg 4 E mux_mul_0_left_sel[3:0] $end
$var reg 4 F mux_mul_0_right_sel[3:0] $end
$var reg 4 G mux_ram_addr_sel[3:0] $end
$var reg 4 H mux_ram_data_sel[3:0] $end
$var reg 3 I state_out[2:0] $end
$comment state is not handled $end
$upscope $end
$scope module dp $end
$var reg 1 J clk $end
$var reg 1 K rst $end
$var reg 1 L r0_en $end
$var reg 1 M r1_en $end
$var reg 1 N r2_en $end
$var reg 1 O r3_en $end
$var reg 1 P r4_en $end
$var reg 1 Q r5_en $end
$var reg 1 R r6_en $end
$var reg 1 S r7_en $end
$var reg 1 T r8_en $end
$var reg 1 U ram_en $end
$var reg 1 V ram_wr $end
$var reg 4 W mux_add_0_left_sel[3:0] $end
$var reg 4 X mux_add_0_right_sel[3:0] $end
$var reg 4 Y mux_mul_0_left_sel[3:0] $end
$var reg 4 Z mux_mul_0_right_sel[3:0] $end
$var reg 4 [ mux_ram_addr_sel[3:0] $end
$var reg 4 \ mux_ram_data_sel[3:0] $end
$var reg 1 ] done $end
$var integer 32 ^ r0_out $end
$var integer 32 _ r1_out $end
$var integer 32 ` r2_out $end
$var integer 32 a r3_out $end
$var integer 32 b r4_out $end
$var integer 32 c r5_out $end
$var integer 32 d r6_out $end
$var integer 32 e r7_out $end
$var integer 32 f r8_out $end
$var integer 32 g mux_ram_addr_out $end
$var integer 32 h mux_mul_0_left_out $end
$var integer 32 i mux_mul_0_right_out $end
$var integer 32 j mux_add_0_left_out $end
$var integer 32 k mux_add_0_right_out $end
$var integer 32 l mux_ram_data_out $end
$var integer 32 m ram_dout $end
$var integer 32 n add_0_out $end
$var integer 32 o mul_0_out $end
$comment ram_mem is not handled $end
$upscope $end
$upscope $end
$enddefinitions $end
#0
0!
1"
1#
1$
0%
0&
1'
0(
0)
1*
0+
0,
0-
b0000 .
b0000 /
b0000 0
b0000 1
b0000 2
b0000 3
b000 4
15
06
17
18
19
0:
0;
1<
0=
0>
1?
0@
0A
0B
b0000 C
b0000 D
b0000 E
b0000 F
b0000 G
b0000 H
b000 I
0J
1K
1L
1M
0N
0O
1P
0Q
0R
1S
0T
0U
0V
b0000 W
b0000 X
b0000 Y
b0000 Z
b0000 [
b0000 \
1]
b0 ^
b0 _
b0 `
b0 a
b0 b
b0 c
b0 d
b0 e
b0 f
b0 g
b0 h
b0 i
b0 j
b0 k
b0 l
b0 m
b0 n
b0 o
#5000000
1!
16
1J
b1 _
b10 b
b11 e
#10000000
0!
06
0J
#15000000
1!
16
1J
#20000000
0!
0"
06
07
0J
0K
#25000000
1!
0#
0$
1%
0'
0*
1,
b001 4
16
08
09
1:
0<
0?
1A
b001 I
1J
0L
0M
1N
0P
0S
1U
#30000000
0!
06
0J
#35000000
1!
0%
1&
b0001 2
b010 4
16
0:
1;
1A
b0001 G
b010 I
1J
0N
1O
b0001 [
b1 g
#40000000
0!
06
0J
#45000000
1!
0&
1(
1)
b0010 2
b011 4
16
0;
1=
1>
1A
b0010 G
b011 I
1J
0O
1Q
1R
b0010 [
b10 g
#50000000
0!
06
0J
#55000000
1!
0(
0)
1+
0,
b0000 2
b100 4
16
0=
0>
1@
0A
b0000 G
b100 I
1J
0Q
0R
1T
0U
b0000 [
b0 g
#60000000
0!
06
0J
#65000000
1!
0+
1,
1-
b0011 2
b101 4
16
0@
1A
1B
b0011 G
b101 I
1J
0T
1U
1V
b0011 [
b11 g
#70000000
0!
06
0J
#75000000
1!
0,
0-
b0000 2
b110 4
16
0A
0B
b0000 G
b110 I
1J
0U
0V
b0000 [
b0 g
