generated_vhdl_test3/datapath_gen.vhdl
-- Complete Datapath (Auto-Generated)
library IEEE;
use IEEE.STD_LOGIC_1164.ALL;
use IEEE.NUMERIC_STD.ALL;
use std.textio.all;

entity Datapath is
    generic (
        DATA_WIDTH : integer := 32;
        ADDR_WIDTH : integer := 10
    );
    Port ( clk, rst : in STD_LOGIC;
           R0_en : in STD_LOGIC;
           R1_en : in STD_LOGIC;
           R10_en : in STD_LOGIC;
           R11_en : in STD_LOGIC;
           R12_en : in STD_LOGIC;
           R13_en : in STD_LOGIC;
           R14_en : in STD_LOGIC;
           R15_en : in STD_LOGIC;
           R16_en : in STD_LOGIC;
           R17_en : in STD_LOGIC;
           R18_en : in STD_LOGIC;
           R19_en : in STD_LOGIC;
           R2_en : in STD_LOGIC;
           R20_en : in STD_LOGIC;
           R21_en : in STD_LOGIC;
           R22_en : in STD_LOGIC;
           R23_en : in STD_LOGIC;
           R3_en : in STD_LOGIC;
           R4_en : in STD_LOGIC;
           R5_en : in STD_LOGIC;
           R6_en : in STD_LOGIC;
           R7_en : in STD_LOGIC;
           R8_en : in STD_LOGIC;
           R9_en : in STD_LOGIC;
           A_en : in STD_LOGIC;
           A_wr : in STD_LOGIC;
           B_en : in STD_LOGIC;
           B_wr : in STD_LOGIC;
           C_en : in STD_LOGIC;
           C_wr : in STD_LOGIC;
           Mux_A_addr_sel : in STD_LOGIC_VECTOR(3 downto 0);
           Mux_Add_0_left_sel : in STD_LOGIC_VECTOR(3 downto 0);
           Mux_Add_0_right_sel : in STD_LOGIC_VECTOR(3 downto 0);
           Mux_B_addr_sel : in STD_LOGIC_VECTOR(3 downto 0);
           Mux_C_addr_sel : in STD_LOGIC_VECTOR(3 downto 0);
           Mux_C_data_sel : in STD_LOGIC_VECTOR(3 downto 0);
           Mux_Mul_0_left_sel : in STD_LOGIC_VECTOR(3 downto 0);
           Mux_Mul_0_right_sel : in STD_LOGIC_VECTOR(3 downto 0);
           done : out STD_LOGIC);
end Datapath;

architecture Behavioral of Datapath is

    -- Register outputs
    signal R0_out : INTEGER := 0;
    signal R1_out : INTEGER := 0;
    signal R10_out : INTEGER := 0;
    signal R11_out : INTEGER := 0;
    signal R12_out : INTEGER := 0;
    signal R13_out : INTEGER := 0;
    signal R14_out : INTEGER := 0;
    signal R15_out : INTEGER := 0;
    signal R16_out : INTEGER := 0;
    signal R17_out : INTEGER := 0;
    signal R18_out : INTEGER := 0;
    signal R19_out : INTEGER := 0;
    signal R2_out : INTEGER := 0;
    signal R20_out : INTEGER := 0;
    signal R21_out : INTEGER := 0;
    signal R22_out : INTEGER := 0;
    signal R23_out : INTEGER := 0;
    signal R3_out : INTEGER := 0;
    signal R4_out : INTEGER := 0;
    signal R5_out : INTEGER := 0;
    signal R6_out : INTEGER := 0;
    signal R7_out : INTEGER := 0;
    signal R8_out : INTEGER := 0;
    signal R9_out : INTEGER := 0;

    -- Mux outputs
    signal Mux_A_addr_out : INTEGER := 0;
    signal Mux_B_addr_out : INTEGER := 0;
    signal Mux_Mul_0_left_out : INTEGER := 0;
    signal Mux_Mul_0_right_out : INTEGER := 0;
    signal Mux_Add_0_left_out : INTEGER := 0;
    signal Mux_Add_0_right_out : INTEGER := 0;
    signal Mux_C_addr_out : INTEGER := 0;
    signal Mux_C_data_out : INTEGER := 0;

    -- Memory data outputs
    signal A_dout : INTEGER := 0;
    signal B_dout : INTEGER := 0;
    signal C_dout : INTEGER := 0;

    -- Arithmetic unit outputs
    signal Add_0_out : INTEGER := 0;
    signal Mul_0_out : INTEGER := 0;

    -- Memory array type and initialization
    type ram_array is array (0 to 2**ADDR_WIDTH-1) of INTEGER;

    impure function init_ram(filename : in string) return ram_array is
        file ram_file : text;
        variable ram_line : line;
        variable temp_int : integer;
        variable temp_ram : ram_array;
        variable status : file_open_status;
    begin
        for i in 0 to 2**ADDR_WIDTH-1 loop
            temp_ram(i) := 0;
        end loop;
        file_open(status, ram_file, filename, read_mode);
        if status = open_ok then
            for i in 0 to 2**ADDR_WIDTH-1 loop
                if not endfile(ram_file) then
                    readline(ram_file, ram_line);
                    read(ram_line, temp_int);
                    temp_ram(i) := temp_int;
                end if;
            end loop;
            file_close(ram_file);
        end if;
        return temp_ram;
    end function;

    signal A_mem : ram_array := init_ram("A_content.txt");
    signal B_mem : ram_array := init_ram("B_content.txt");
    signal C_mem : ram_array := init_ram("C_content.txt");

begin

    done <= '1';  -- Always done for now

    -- Register update process
    process(clk)
    begin
        if rising_edge(clk) then
            if R0_en = '1' then R0_out <= 0; end if;
            if R1_en = '1' then R1_out <= 0; end if;
            if R10_en = '1' then R10_out <= 2; end if;
            if R11_en = '1' then R11_out <= 2; end if;
            if R12_en = '1' then R12_out <= A_dout; end if;
            if R13_en = '1' then R13_out <= B_dout; end if;
            if R14_en = '1' then R14_out <= Add_0_out; end if;
            if R15_en = '1' then R15_out <= Mul_0_out; end if;
            if R16_en = '1' then R16_out <= 3; end if;
            if R17_en = '1' then R17_out <= 3; end if;
            if R18_en = '1' then R18_out <= A_dout; end if;
            if R19_en = '1' then R19_out <= B_dout; end if;
            if R2_en = '1' then R2_out <= A_dout; end if;
            if R20_en = '1' then R20_out <= Add_0_out; end if;
            if R21_en = '1' then R21_out <= Mul_0_out; end if;
            if R22_en = '1' then R22_out <= 0; end if;
            if R23_en = '1' then R23_out <= Add_0_out; end if;
            if R3_en = '1' then R3_out <= B_dout; end if;
            if R4_en = '1' then R4_out <= 1; end if;
            if R5_en = '1' then R5_out <= 1; end if;
            if R6_en = '1' then R6_out <= A_dout; end if;
            if R7_en = '1' then R7_out <= B_dout; end if;
            if R8_en = '1' then R8_out <= Mul_0_out; end if;
            if R9_en = '1' then R9_out <= Mul_0_out; end if;
        end if;
    end process;

    -- Multiplexer logic
    Mux_A_addr_out <= R0_out when Mux_A_addr_sel = "0000" else
               R4_out when Mux_A_addr_sel = "0001" else
               R10_out when Mux_A_addr_sel = "0010" else
               R16_out when Mux_A_addr_sel = "0011" else 0;

    Mux_B_addr_out <= R1_out when Mux_B_addr_sel = "0000" else
               R5_out when Mux_B_addr_sel = "0001" else
               R11_out when Mux_B_addr_sel = "0010" else
               R17_out when Mux_B_addr_sel = "0011" else 0;

    Mux_Mul_0_left_out <= R2_out when Mux_Mul_0_left_sel = "0000" else
               R6_out when Mux_Mul_0_left_sel = "0001" else
               R12_out when Mux_Mul_0_left_sel = "0010" else
               R18_out when Mux_Mul_0_left_sel = "0011" else 0;

    Mux_Mul_0_right_out <= R3_out when Mux_Mul_0_right_sel = "0000" else
               R7_out when Mux_Mul_0_right_sel = "0001" else
               R13_out when Mux_Mul_0_right_sel = "0010" else
               R19_out when Mux_Mul_0_right_sel = "0011" else 0;

    Mux_Add_0_left_out <= R8_out when Mux_Add_0_left_sel = "0000" else
               R14_out when Mux_Add_0_left_sel = "0001" else
               R20_out when Mux_Add_0_left_sel = "0010" else 0;

    Mux_Add_0_right_out <= R9_out when Mux_Add_0_right_sel = "0000" else
               R15_out when Mux_Add_0_right_sel = "0001" else
               R21_out when Mux_Add_0_right_sel = "0010" else 0;

    Mux_C_addr_out <= R22_out when Mux_C_addr_sel = "0000" else
               0;

    Mux_C_data_out <= R23_out when Mux_C_data_sel = "0000" else
               0;

    -- Memory read logic (combinational)
    A_dout <= A_mem(Mux_A_addr_out);
    B_dout <= B_mem(Mux_B_addr_out);
    C_dout <= C_mem(Mux_C_addr_out);

    -- Memory write processes
    process(clk)
    begin
        if rising_edge(clk) then
            if C_wr = '1' then
                C_mem(Mux_C_addr_out) <= Mux_C_data_out;
            end if;
        end if;
    end process;

    -- Arithmetic units (combinational)
    Mul_0_out <= Mux_Mul_0_left_out * Mux_Mul_0_right_out;
    Add_0_out <= Mux_Add_0_left_out + Mux_Add_0_right_out;

end Behavioral;

generated_vhdl_test3/controller.vhdl
-- FSM Controller
library IEEE;
use IEEE.STD_LOGIC_1164.ALL;
use IEEE.NUMERIC_STD.ALL;

entity Controller is
    Port ( clk, rst : in STD_LOGIC;
           R0_en : out STD_LOGIC;
           R1_en : out STD_LOGIC;
           R10_en : out STD_LOGIC;
           R11_en : out STD_LOGIC;
           R12_en : out STD_LOGIC;
           R13_en : out STD_LOGIC;
           R14_en : out STD_LOGIC;
           R15_en : out STD_LOGIC;
           R16_en : out STD_LOGIC;
           R17_en : out STD_LOGIC;
           R18_en : out STD_LOGIC;
           R19_en : out STD_LOGIC;
           R2_en : out STD_LOGIC;
           R20_en : out STD_LOGIC;
           R21_en : out STD_LOGIC;
           R22_en : out STD_LOGIC;
           R23_en : out STD_LOGIC;
           R3_en : out STD_LOGIC;
           R4_en : out STD_LOGIC;
           R5_en : out STD_LOGIC;
           R6_en : out STD_LOGIC;
           R7_en : out STD_LOGIC;
           R8_en : out STD_LOGIC;
           R9_en : out STD_LOGIC;
           A_en : out STD_LOGIC;
           A_wr : out STD_LOGIC;
           B_en : out STD_LOGIC;
           B_wr : out STD_LOGIC;
           C_en : out STD_LOGIC;
           C_wr : out STD_LOGIC;
           Mux_A_addr_sel : out STD_LOGIC_VECTOR(3 downto 0);
           Mux_Add_0_left_sel : out STD_LOGIC_VECTOR(3 downto 0);
           Mux_Add_0_right_sel : out STD_LOGIC_VECTOR(3 downto 0);
           Mux_B_addr_sel : out STD_LOGIC_VECTOR(3 downto 0);
           Mux_C_addr_sel : out STD_LOGIC_VECTOR(3 downto 0);
           Mux_C_data_sel : out STD_LOGIC_VECTOR(3 downto 0);
           Mux_Mul_0_left_sel : out STD_LOGIC_VECTOR(3 downto 0);
           Mux_Mul_0_right_sel : out STD_LOGIC_VECTOR(3 downto 0);
           state_out : out STD_LOGIC_VECTOR(3 downto 0));
end Controller;

architecture Behavioral of Controller is
    type state_type is (S0, S1, S2, S3, S4, S5, S6, S7, S_END);
    signal state : state_type := S0;
    function encode_state(s: state_type) return STD_LOGIC_VECTOR is
    begin
        case s is
            when S0 => return std_logic_vector(to_unsigned(0, 4));
            when S1 => return std_logic_vector(to_unsigned(1, 4));
            when S2 => return std_logic_vector(to_unsigned(2, 4));
            when S3 => return std_logic_vector(to_unsigned(3, 4));
            when S4 => return std_logic_vector(to_unsigned(4, 4));
            when S5 => return std_logic_vector(to_unsigned(5, 4));
            when S6 => return std_logic_vector(to_unsigned(6, 4));
            when S7 => return std_logic_vector(to_unsigned(7, 4));
            when S_END => return std_logic_vector(to_unsigned(8, 4));
        end case;
    end function;
begin

    process(clk, rst)
    begin
        if rst = '1' then state <= S0;
        elsif rising_edge(clk) then
            case state is
                when S0 => state <= S1;
                when S1 => state <= S2;
                when S2 => state <= S3;
                when S3 => state <= S4;
                when S4 => state <= S5;
                when S5 => state <= S6;
                when S6 => state <= S7;
                when S7 => state <= S_END;
                when others => state <= S_END;
            end case;
        end if;
    end process;

    state_out <= encode_state(state);

    process(state)
    begin
        R0_en <= '0';
        R1_en <= '0';
        R10_en <= '0';
        R11_en <= '0';
        R12_en <= '0';
        R13_en <= '0';
        R14_en <= '0';
        R15_en <= '0';
        R16_en <= '0';
        R17_en <= '0';
        R18_en <= '0';
        R19_en <= '0';
        R2_en <= '0';
        R20_en <= '0';
        R21_en <= '0';
        R22_en <= '0';
        R23_en <= '0';
        R3_en <= '0';
        R4_en <= '0';
        R5_en <= '0';
        R6_en <= '0';
        R7_en <= '0';
        R8_en <= '0';
        R9_en <= '0';
        A_en <= '0';
        A_wr <= '0';
        B_en <= '0';
        B_wr <= '0';
        C_en <= '0';
        C_wr <= '0';
        Mux_A_addr_sel <= (others => '0');
        Mux_Add_0_left_sel <= (others => '0');
        Mux_Add_0_right_sel <= (others => '0');
        Mux_B_addr_sel <= (others => '0');
        Mux_C_addr_sel <= (others => '0');
        Mux_C_data_sel <= (others => '0');
        Mux_Mul_0_left_sel <= (others => '0');
        Mux_Mul_0_right_sel <= (others => '0');
        case state is
            when S0 =>
                R22_en <= '1';
                R0_en <= '1';
                R1_en <= '1';
                R4_en <= '1';
                R5_en <= '1';
                R10_en <= '1';
                R11_en <= '1';
                R16_en <= '1';
                R17_en <= '1';
            when S1 =>
                R2_en <= '1';
                R3_en <= '1';
                A_en <= '1';
                B_en <= '1';
                Mux_A_addr_sel <= std_logic_vector(to_unsigned(0, 4));
                Mux_B_addr_sel <= std_logic_vector(to_unsigned(0, 4));
            when S2 =>
                R8_en <= '1';
                R6_en <= '1';
                R7_en <= '1';
                A_en <= '1';
                B_en <= '1';
                Mux_Mul_0_left_sel <= std_logic_vector(to_unsigned(0, 4));
                Mux_Mul_0_right_sel <= std_logic_vector(to_unsigned(0, 4));
                Mux_A_addr_sel <= std_logic_vector(to_unsigned(1, 4));
                Mux_B_addr_sel <= std_logic_vector(to_unsigned(1, 4));
            when S3 =>
                R9_en <= '1';
                R12_en <= '1';
                R13_en <= '1';
                A_en <= '1';
                B_en <= '1';
                Mux_Mul_0_left_sel <= std_logic_vector(to_unsigned(1, 4));
                Mux_Mul_0_right_sel <= std_logic_vector(to_unsigned(1, 4));
                Mux_A_addr_sel <= std_logic_vector(to_unsigned(2, 4));
                Mux_B_addr_sel <= std_logic_vector(to_unsigned(2, 4));
            when S4 =>
                R14_en <= '1';
                R15_en <= '1';
                R18_en <= '1';
                R19_en <= '1';
                A_en <= '1';
                B_en <= '1';
                Mux_Add_0_left_sel <= std_logic_vector(to_unsigned(0, 4));
                Mux_Add_0_right_sel <= std_logic_vector(to_unsigned(0, 4));
                Mux_Mul_0_left_sel <= std_logic_vector(to_unsigned(2, 4));
                Mux_Mul_0_right_sel <= std_logic_vector(to_unsigned(2, 4));
                Mux_A_addr_sel <= std_logic_vector(to_unsigned(3, 4));
                Mux_B_addr_sel <= std_logic_vector(to_unsigned(3, 4));
            when S5 =>
                R20_en <= '1';
                R21_en <= '1';
                Mux_Add_0_left_sel <= std_logic_vector(to_unsigned(1, 4));
                Mux_Add_0_right_sel <= std_logic_vector(to_unsigned(1, 4));
                Mux_Mul_0_left_sel <= std_logic_vector(to_unsigned(3, 4));
                Mux_Mul_0_right_sel <= std_logic_vector(to_unsigned(3, 4));
            when S6 =>
                R23_en <= '1';
                Mux_Add_0_left_sel <= std_logic_vector(to_unsigned(2, 4));
                Mux_Add_0_right_sel <= std_logic_vector(to_unsigned(2, 4));
            when S7 =>
                C_en <= '1';
                C_wr <= '1';
                Mux_C_addr_sel <= std_logic_vector(to_unsigned(0, 4));
                Mux_C_data_sel <= std_logic_vector(to_unsigned(0, 4));
            when others => null;
        end case;
    end process;
end Behavioral;

generated_vhdl_test3/testbench.vhdl
-- Testbench for HLS Generated Design
library IEEE;
use IEEE.STD_LOGIC_1164.ALL;
use IEEE.NUMERIC_STD.ALL;

entity testbench is
end testbench;

architecture Behavioral of testbench is
    -- Clock and reset
    signal clk : STD_LOGIC := '0';
    signal rst : STD_LOGIC := '1';
    constant CLK_PERIOD : time := 10 ns;

    -- Control signals (connect Controller to Datapath)
    signal R0_en : STD_LOGIC;
    signal R1_en : STD_LOGIC;
    signal R10_en : STD_LOGIC;
    signal R11_en : STD_LOGIC;
    signal R12_en : STD_LOGIC;
    signal R13_en : STD_LOGIC;
    signal R14_en : STD_LOGIC;
    signal R15_en : STD_LOGIC;
    signal R16_en : STD_LOGIC;
    signal R17_en : STD_LOGIC;
    signal R18_en : STD_LOGIC;
    signal R19_en : STD_LOGIC;
    signal R2_en : STD_LOGIC;
    signal R20_en : STD_LOGIC;
    signal R21_en : STD_LOGIC;
    signal R22_en : STD_LOGIC;
    signal R23_en : STD_LOGIC;
    signal R3_en : STD_LOGIC;
    signal R4_en : STD_LOGIC;
    signal R5_en : STD_LOGIC;
    signal R6_en : STD_LOGIC;
    signal R7_en : STD_LOGIC;
    signal R8_en : STD_LOGIC;
    signal R9_en : STD_LOGIC;
    signal A_en : STD_LOGIC;
    signal A_wr : STD_LOGIC;
    signal B_en : STD_LOGIC;
    signal B_wr : STD_LOGIC;
    signal C_en : STD_LOGIC;
    signal C_wr : STD_LOGIC;
    signal Mux_A_addr_sel : STD_LOGIC_VECTOR(3 downto 0);
    signal Mux_Add_0_left_sel : STD_LOGIC_VECTOR(3 downto 0);
    signal Mux_Add_0_right_sel : STD_LOGIC_VECTOR(3 downto 0);
    signal Mux_B_addr_sel : STD_LOGIC_VECTOR(3 downto 0);
    signal Mux_C_addr_sel : STD_LOGIC_VECTOR(3 downto 0);
    signal Mux_C_data_sel : STD_LOGIC_VECTOR(3 downto 0);
    signal Mux_Mul_0_left_sel : STD_LOGIC_VECTOR(3 downto 0);
    signal Mux_Mul_0_right_sel : STD_LOGIC_VECTOR(3 downto 0);
    signal state_out : STD_LOGIC_VECTOR(3 downto 0);

    -- Done signal from Datapath
    signal done : STD_LOGIC;

begin

    -- Clock generation
    clk <= not clk after CLK_PERIOD / 2;

    -- Controller instantiation
    CTRL: entity work.Controller
        port map (
            clk => clk,
            rst => rst,
            R0_en => R0_en,
            R1_en => R1_en,
            R10_en => R10_en,
            R11_en => R11_en,
            R12_en => R12_en,
            R13_en => R13_en,
            R14_en => R14_en,
            R15_en => R15_en,
            R16_en => R16_en,
            R17_en => R17_en,
            R18_en => R18_en,
            R19_en => R19_en,
            R2_en => R2_en,
            R20_en => R20_en,
            R21_en => R21_en,
            R22_en => R22_en,
            R23_en => R23_en,
            R3_en => R3_en,
            R4_en => R4_en,
            R5_en => R5_en,
            R6_en => R6_en,
            R7_en => R7_en,
            R8_en => R8_en,
            R9_en => R9_en,
            A_en => A_en,
            A_wr => A_wr,
            B_en => B_en,
            B_wr => B_wr,
            C_en => C_en,
            C_wr => C_wr,
            Mux_A_addr_sel => Mux_A_addr_sel,
            Mux_Add_0_left_sel => Mux_Add_0_left_sel,
            Mux_Add_0_right_sel => Mux_Add_0_right_sel,
            Mux_B_addr_sel => Mux_B_addr_sel,
            Mux_C_addr_sel => Mux_C_addr_sel,
            Mux_C_data_sel => Mux_C_data_sel,
            Mux_Mul_0_left_sel => Mux_Mul_0_left_sel,
            Mux_Mul_0_right_sel => Mux_Mul_0_right_sel,
            state_out => state_out
        );

    -- Datapath instantiation
    DP: entity work.Datapath
        port map (
            clk => clk,
            rst => rst,
            R0_en => R0_en,
            R1_en => R1_en,
            R10_en => R10_en,
            R11_en => R11_en,
            R12_en => R12_en,
            R13_en => R13_en,
            R14_en => R14_en,
            R15_en => R15_en,
            R16_en => R16_en,
            R17_en => R17_en,
            R18_en => R18_en,
            R19_en => R19_en,
            R2_en => R2_en,
            R20_en => R20_en,
            R21_en => R21_en,
            R22_en => R22_en,
            R23_en => R23_en,
            R3_en => R3_en,
            R4_en => R4_en,
            R5_en => R5_en,
            R6_en => R6_en,
            R7_en => R7_en,
            R8_en => R8_en,
            R9_en => R9_en,
            A_en => A_en,
            A_wr => A_wr,
            B_en => B_en,
            B_wr => B_wr,
            C_en => C_en,
            C_wr => C_wr,
            Mux_A_addr_sel => Mux_A_addr_sel,
            Mux_Add_0_left_sel => Mux_Add_0_left_sel,
            Mux_Add_0_right_sel => Mux_Add_0_right_sel,
            Mux_B_addr_sel => Mux_B_addr_sel,
            Mux_C_addr_sel => Mux_C_addr_sel,
            Mux_C_data_sel => Mux_C_data_sel,
            Mux_Mul_0_left_sel => Mux_Mul_0_left_sel,
            Mux_Mul_0_right_sel => Mux_Mul_0_right_sel,
            done => done
        );

    -- Stimulus process
    process
    begin
        rst <= '1';
        wait for CLK_PERIOD * 2;
        rst <= '0';
        wait for CLK_PERIOD * 11;  -- Run all states
        wait;
    end process;

end Behavioral;

generated_vhdl_test3/wave.vcd
$date
  Tue Feb  3 22:28:50 2026
$end
$version
  GHDL v0
$end
$timescale
  1 fs
$end
$scope module standard $end
$upscope $end
$scope module textio $end
$upscope $end
$scope module std_logic_1164 $end
$upscope $end
$scope module numeric_std $end
$upscope $end
$scope module testbench $end
$var reg 1 ! clk $end
$var reg 1 " rst $end
$var reg 1 # r0_en $end
$var reg 1 $ r1_en $end
$var reg 1 % r10_en $end
$var reg 1 & r11_en $end
$var reg 1 ' r12_en $end
$var reg 1 ( r13_en $end
$var reg 1 ) r14_en $end
$var reg 1 * r15_en $end
$var reg 1 + r16_en $end
$var reg 1 , r17_en $end
$var reg 1 - r18_en $end
$var reg 1 . r19_en $end
$var reg 1 / r2_en $end
$var reg 1 0 r20_en $end
$var reg 1 1 r21_en $end
$var reg 1 2 r22_en $end
$var reg 1 3 r23_en $end
$var reg 1 4 r3_en $end
$var reg 1 5 r4_en $end
$var reg 1 6 r5_en $end
$var reg 1 7 r6_en $end
$var reg 1 8 r7_en $end
$var reg 1 9 r8_en $end
$var reg 1 : r9_en $end
$var reg 1 ; a_en $end
$var reg 1 < a_wr $end
$var reg 1 = b_en $end
$var reg 1 > b_wr $end
$var reg 1 ? c_en $end
$var reg 1 @ c_wr $end
$var reg 4 A mux_a_addr_sel[3:0] $end
$var reg 4 B mux_add_0_left_sel[3:0] $end
$var reg 4 C mux_add_0_right_sel[3:0] $end
$var reg 4 D mux_b_addr_sel[3:0] $end
$var reg 4 E mux_c_addr_sel[3:0] $end
$var reg 4 F mux_c_data_sel[3:0] $end
$var reg 4 G mux_mul_0_left_sel[3:0] $end
$var reg 4 H mux_mul_0_right_sel[3:0] $end
$var reg 4 I state_out[3:0] $end
$var reg 1 J done $end
$scope module ctrl $end
$var reg 1 K clk $end
$var reg 1 L rst $end
$var reg 1 M r0_en $end
$var reg 1 N r1_en $end
$var reg 1 O r10_en $end
$var reg 1 P r11_en $end
$var reg 1 Q r12_en $end
$var reg 1 R r13_en $end
$var reg 1 S r14_en $end
$var reg 1 T r15_en $end
$var reg 1 U r16_en $end
$var reg 1 V r17_en $end
$var reg 1 W r18_en $end
$var reg 1 X r19_en $end
$var reg 1 Y r2_en $end
$var reg 1 Z r20_en $end
$var reg 1 [ r21_en $end
$var reg 1 \ r22_en $end
$var reg 1 ] r23_en $end
$var reg 1 ^ r3_en $end
$var reg 1 _ r4_en $end
$var reg 1 ` r5_en $end
$var reg 1 a r6_en $end
$var reg 1 b r7_en $end
$var reg 1 c r8_en $end
$var reg 1 d r9_en $end
$var reg 1 e a_en $end
$var reg 1 f a_wr $end
$var reg 1 g b_en $end
$var reg 1 h b_wr $end
$var reg 1 i c_en $end
$var reg 1 j c_wr $end
$var reg 4 k mux_a_addr_sel[3:0] $end
$var reg 4 l mux_add_0_left_sel[3:0] $end
$var reg 4 m mux_add_0_right_sel[3:0] $end
$var reg 4 n mux_b_addr_sel[3:0] $end
$var reg 4 o mux_c_addr_sel[3:0] $end
$var reg 4 p mux_c_data_sel[3:0] $end
$var reg 4 q mux_mul_0_left_sel[3:0] $end
$var reg 4 r mux_mul_0_right_sel[3:0] $end
$var reg 4 s state_out[3:0] $end
$comment state is not handled $end
$upscope $end
$scope module dp $end
$var reg 1 t clk $end
$var reg 1 u rst $end
$var reg 1 v r0_en $end
$var reg 1 w r1_en $end
$var reg 1 x r10_en $end
$var reg 1 y r11_en $end
$var reg 1 z r12_en $end
$var reg 1 { r13_en $end
$var reg 1 | r14_en $end
$var reg 1 } r15_en $end
$var reg 1 !" r16_en $end
$var reg 1 "" r17_en $end
$var reg 1 #" r18_en $end
$var reg 1 $" r19_en $end
$var reg 1 %" r2_en $end
$var reg 1 &" r20_en $end
$var reg 1 '" r21_en $end
$var reg 1 (" r22_en $end
$var reg 1 )" r23_en $end
$var reg 1 *" r3_en $end
$var reg 1 +" r4_en $end
$var reg 1 ," r5_en $end
$var reg 1 -" r6_en $end
$var reg 1 ." r7_en $end
$var reg 1 /" r8_en $end
$var reg 1 0" r9_en $end
$var reg 1 1" a_en $end
$var reg 1 2" a_wr $end
$var reg 1 3" b_en $end
$var reg 1 4" b_wr $end
$var reg 1 5" c_en $end
$var reg 1 6" c_wr $end
$var reg 4 7" mux_a_addr_sel[3:0] $end
$var reg 4 8" mux_add_0_left_sel[3:0] $end
$var reg 4 9" mux_add_0_right_sel[3:0] $end
$var reg 4 :" mux_b_addr_sel[3:0] $end
$var reg 4 ;" mux_c_addr_sel[3:0] $end
$var reg 4 <" mux_c_data_sel[3:0] $end
$var reg 4 =" mux_mul_0_left_sel[3:0] $end
$var reg 4 >" mux_mul_0_right_sel[3:0] $end
$var reg 1 ?" done $end
$var integer 32 @" r0_out $end
$var integer 32 A" r1_out $end
$var integer 32 B" r10_out $end
$var integer 32 C" r11_out $end
$var integer 32 D" r12_out $end
$var integer 32 E" r13_out $end
$var integer 32 F" r14_out $end
$var integer 32 G" r15_out $end
$var integer 32 H" r16_out $end
$var integer 32 I" r17_out $end
$var integer 32 J" r18_out $end
$var integer 32 K" r19_out $end
$var integer 32 L" r2_out $end
$var integer 32 M" r20_out $end
$var integer 32 N" r21_out $end
$var integer 32 O" r22_out $end
$var integer 32 P" r23_out $end
$var integer 32 Q" r3_out $end
$var integer 32 R" r4_out $end
$var integer 32 S" r5_out $end
$var integer 32 T" r6_out $end
$var integer 32 U" r7_out $end
$var integer 32 V" r8_out $end
$var integer 32 W" r9_out $end
$var integer 32 X" mux_a_addr_out $end
$var integer 32 Y" mux_b_addr_out $end
$var integer 32 Z" mux_mul_0_left_out $end
$var integer 32 [" mux_mul_0_right_out $end
$var integer 32 \" mux_add_0_left_out $end
$var integer 32 ]" mux_add_0_right_out $end
$var integer 32 ^" mux_c_addr_out $end
$var integer 32 _" mux_c_data_out $end
$var integer 32 `" a_dout $end
$var integer 32 a" b_dout $end
$var integer 32 b" c_dout $end
$var integer 32 c" add_0_out $end
$var integer 32 d" mul_0_out $end
$comment a_mem is not handled $end
$comment b_mem is not handled $end
$comment c_mem is not handled $end
$upscope $end
$upscope $end
$enddefinitions $end
#0
0!
1"
1#
1$
1%
1&
0'
0(
0)
0*
1+
1,
0-
0.
0/
00
01
12
03
04
15
16
07
08
09
0:
0;
0<
0=
0>
0?
0@
b0000 A
b0000 B
b0000 C
b0000 D
b0000 E
b0000 F
b0000 G
b0000 H
b0000 I
1J
0K
1L
1M
1N
1O
1P
0Q
0R
0S
0T
1U
1V
0W
0X
0Y
0Z
0[
1\
0]
0^
1_
1`
0a
0b
0c
0d
0e
0f
0g
0h
0i
0j
b0000 k
b0000 l
b0000 m
b0000 n
b0000 o
b0000 p
b0000 q
b0000 r
b0000 s
0t
1u
1v
1w
1x
1y
0z
0{
0|
0}
1!"
1""
0#"
0$"
0%"
0&"
0'"
1("
0)"
0*"
1+"
1,"
0-"
0."
0/"
00"
01"
02"
03"
04"
05"
06"
b0000 7"
b0000 8"
b0000 9"
b0000 :"
b0000 ;"
b0000 <"
b0000 ="
b0000 >"
1?"
b0 @"
b0 A"
b0 B"
b0 C"
b0 D"
b0 E"
b0 F"
b0 G"
b0 H"
b0 I"
b0 J"
b0 K"
b0 L"
b0 M"
b0 N"
b0 O"
b0 P"
b0 Q"
b0 R"
b0 S"
b0 T"
b0 U"
b0 V"
b0 W"
b0 X"
b0 Y"
b0 Z"
b0 ["
b0 \"
b0 ]"
b0 ^"
b0 _"
b1010 `"
b1010 a"
b1010 b"
b0 c"
b0 d"
#5000000
1!
1K
1t
b10 B"
b10 C"
b11 H"
b11 I"
b1 R"
b1 S"
#10000000
0!
0K
0t
#15000000
1!
1K
1t
#20000000
0!
0"
0K
0L
0t
0u
#25000000
1!
0#
0$
0%
0&
0+
0,
1/
02
14
05
06
1;
1=
b0001 I
1K
0M
0N
0O
0P
0U
0V
1Y
0\
1^
0_
0`
1e
1g
b0001 s
1t
0v
0w
0x
0y
0!"
0""
1%"
0("
1*"
0+"
0,"
11"
13"
#30000000
0!
0K
0t
#35000000
1!
0/
04
17
18
19
b0001 A
b0001 D
b0010 I
1K
0Y
0^
1a
1b
1c
1e
1g
b0001 k
b0001 n
b0010 s
1t
0%"
0*"
1-"
1."
1/"
b0001 7"
b0001 :"
b1010 L"
b1010 Q"
b1 X"
b1 Y"
b1010 Z"
b1010 ["
b10100 `"
b10100 a"
b1100100 d"
#40000000
0!
0K
0t
#45000000
1!
1'
1(
07
08
09
1:
b0010 A
b0010 D
b0001 G
b0001 H
b0011 I
1K
1Q
1R
0a
0b
0c
1d
1e
1g
b0010 k
b0010 n
b0001 q
b0001 r
b0011 s
1t
1z
1{
0-"
0."
0/"
10"
b0010 7"
b0010 :"
b0001 ="
b0001 >"
b10100 T"
b10100 U"
b1100100 V"
b10 X"
b10 Y"
b10100 Z"
b10100 ["
b1100100 \"
b1100100 `"
b1100100 a"
b1100100 c"
b110010000 d"
#50000000
0!
0K
0t
#55000000
1!
0'
0(
1)
1*
1-
1.
0:
b0011 A
b0011 D
b0010 G
b0010 H
b0100 I
1K
0Q
0R
1S
1T
1W
1X
0d
1e
1g
b0011 k
b0011 n
b0010 q
b0010 r
b0100 s
1t
0z
0{
1|
1}
1#"
1$"
00"
b0011 7"
b0011 :"
b0010 ="
b0010 >"
b1100100 D"
b1100100 E"
b110010000 W"
b11 X"
b11 Y"
b1100100 Z"
b1100100 ["
b110010000 ]"
b0 `"
b0 a"
b111110100 c"
b10011100010000 d"
#60000000
0!
0K
0t
#65000000
1!
0)
0*
0-
0.
10
11
0;
0=
b0000 A
b0001 B
b0001 C
b0000 D
b0011 G
b0011 H
b0101 I
1K
0S
0T
0W
0X
1Z
1[
0e
0g
b0000 k
b0001 l
b0001 m
b0000 n
b0011 q
b0011 r
b0101 s
1t
0|
0}
0#"
0$"
1&"
1'"
01"
03"
b0000 7"
b0001 8"
b0001 9"
b0000 :"
b0011 ="
b0011 >"
b111110100 F"
b10011100010000 G"
b0 X"
b0 Y"
b0 Z"
b0 ["
b111110100 \"
b10011100010000 ]"
b1010 `"
b1010 a"
b10100100000100 c"
b0 d"
#70000000
0!
0K
0t
